{
  "data": [
    { "evaluation": 87, "time": 0.0010431999107822776, "iteration": 0 },
    { "evaluation": 87, "time": 0.12711629993282259, "iteration": 1 },
    { "evaluation": 93, "time": 0.2207774999551475, "iteration": 2 },
    { "evaluation": 93, "time": 2.2285143999615684, "iteration": 44 },
    { "evaluation": 93, "time": 2.2687851999653503, "iteration": 45 },
    { "evaluation": 93, "time": 2.3088569999672472, "iteration": 46 },
    { "evaluation": 93, "time": 2.3529712999006733, "iteration": 47 },
    { "evaluation": 93, "time": 2.3928534999722615, "iteration": 48 },
    { "evaluation": 93, "time": 2.4323740999680012, "iteration": 49 },
    { "evaluation": 93, "time": 2.475780599983409, "iteration": 50 },
    { "evaluation": 93, "time": 2.5164930999744684, "iteration": 51 },
    { "evaluation": 93, "time": 2.5567113999277353, "iteration": 52 },
    { "evaluation": 93, "time": 2.597318399930373, "iteration": 53 },
    { "evaluation": 93, "time": 2.637953299912624, "iteration": 54 },
    { "evaluation": 93, "time": 2.678381099947728, "iteration": 55 },
    { "evaluation": 93, "time": 2.7280562999658287, "iteration": 56 },
    { "evaluation": 93, "time": 2.775198599905707, "iteration": 57 },
    { "evaluation": 93, "time": 2.8227081999648362, "iteration": 58 },
    { "evaluation": 93, "time": 2.8764505999861285, "iteration": 59 },
    { "evaluation": 93, "time": 2.9316353999311104, "iteration": 60 },
    { "evaluation": 93, "time": 2.982406099908985, "iteration": 61 },
    { "evaluation": 93, "time": 3.032322399900295, "iteration": 62 },
    { "evaluation": 93, "time": 3.081993200001307, "iteration": 63 },
    { "evaluation": 93, "time": 3.1309564999537542, "iteration": 64 },
    { "evaluation": 93, "time": 3.190242199925706, "iteration": 65 },
    { "evaluation": 93, "time": 3.2546809999039397, "iteration": 66 },
    { "evaluation": 93, "time": 3.307716899900697, "iteration": 67 },
    { "evaluation": 93, "time": 3.3609222999075428, "iteration": 68 },
    { "evaluation": 93, "time": 3.4135812999447808, "iteration": 69 },
    { "evaluation": 93, "time": 3.465751299983822, "iteration": 70 },
    { "evaluation": 93, "time": 3.51695789990481, "iteration": 71 },
    { "evaluation": 93, "time": 3.568213199963793, "iteration": 72 },
    { "evaluation": 93, "time": 3.6233513999031857, "iteration": 73 },
    { "evaluation": 93, "time": 3.6748628999339417, "iteration": 74 },
    { "evaluation": 93, "time": 3.7272218000143766, "iteration": 75 },
    { "evaluation": 93, "time": 3.7773015999700874, "iteration": 76 },
    { "evaluation": 93, "time": 3.8243516999064013, "iteration": 77 },
    { "evaluation": 93, "time": 3.873318800004199, "iteration": 78 },
    { "evaluation": 93, "time": 3.9210560999345034, "iteration": 79 },
    { "evaluation": 93, "time": 3.967118199914694, "iteration": 80 },
    { "evaluation": 93, "time": 4.012462300015613, "iteration": 81 },
    { "evaluation": 93, "time": 4.057907199952751, "iteration": 82 },
    { "evaluation": 93, "time": 4.10086839995347, "iteration": 83 },
    { "evaluation": 93, "time": 4.144346799934283, "iteration": 84 },
    { "evaluation": 93, "time": 4.187412099912763, "iteration": 85 },
    { "evaluation": 93, "time": 4.232803799910471, "iteration": 86 },
    { "evaluation": 93, "time": 4.274510399904102, "iteration": 87 },
    { "evaluation": 93, "time": 4.315789599902928, "iteration": 88 },
    { "evaluation": 93, "time": 4.357921299990267, "iteration": 89 },
    { "evaluation": 93, "time": 4.399552299990319, "iteration": 90 },
    { "evaluation": 93, "time": 4.440962899941951, "iteration": 91 },
    { "evaluation": 93, "time": 4.483917300007306, "iteration": 92 },
    { "evaluation": 93, "time": 4.527007299941033, "iteration": 93 },
    { "evaluation": 93, "time": 4.569981699925847, "iteration": 94 },
    { "evaluation": 93, "time": 4.614169799955562, "iteration": 95 },
    { "evaluation": 93, "time": 4.658361300011165, "iteration": 96 },
    { "evaluation": 93, "time": 4.702559700002894, "iteration": 97 },
    { "evaluation": 93, "time": 4.748687899904326, "iteration": 98 },
    { "evaluation": 93, "time": 4.798999799997546, "iteration": 99 },
    { "evaluation": 93, "time": 4.845103099942207, "iteration": 100 },
    { "evaluation": 93, "time": 4.890863899956457, "iteration": 101 },
    { "evaluation": 93, "time": 4.934132699971087, "iteration": 102 },
    { "evaluation": 93, "time": 4.977658899966627, "iteration": 103 },
    { "evaluation": 93, "time": 5.022131099947728, "iteration": 104 },
    { "evaluation": 93, "time": 5.066683899960481, "iteration": 105 },
    { "evaluation": 93, "time": 5.109875199967064, "iteration": 106 },
    { "evaluation": 93, "time": 5.19272309995722, "iteration": 107 },
    { "evaluation": 93, "time": 5.245877599925734, "iteration": 108 },
    { "evaluation": 93, "time": 5.300440399907529, "iteration": 109 },
    { "evaluation": 93, "time": 5.352835699915886, "iteration": 110 },
    { "evaluation": 93, "time": 5.404788299929351, "iteration": 111 },
    { "evaluation": 93, "time": 5.459022099967115, "iteration": 112 },
    { "evaluation": 93, "time": 5.508745500002988, "iteration": 113 },
    { "evaluation": 93, "time": 5.557524099946022, "iteration": 114 },
    { "evaluation": 93, "time": 5.604087799903937, "iteration": 115 },
    { "evaluation": 93, "time": 5.650519899907522, "iteration": 116 },
    { "evaluation": 93, "time": 5.695132199907675, "iteration": 117 },
    { "evaluation": 93, "time": 5.739789999905042, "iteration": 118 },
    { "evaluation": 93, "time": 5.783573099994101, "iteration": 119 },
    { "evaluation": 93, "time": 5.827760399901308, "iteration": 120 },
    { "evaluation": 93, "time": 5.870521700009704, "iteration": 121 },
    { "evaluation": 93, "time": 5.913066899986006, "iteration": 122 },
    { "evaluation": 93, "time": 5.954738499945961, "iteration": 123 },
    { "evaluation": 93, "time": 5.995882999966852, "iteration": 124 },
    { "evaluation": 93, "time": 6.04222129995469, "iteration": 125 },
    { "evaluation": 93, "time": 6.086834399960935, "iteration": 126 },
    { "evaluation": 93, "time": 6.129180699936114, "iteration": 127 },
    { "evaluation": 93, "time": 6.17152949993033, "iteration": 128 },
    { "evaluation": 93, "time": 6.212521099951118, "iteration": 129 },
    { "evaluation": 93, "time": 6.252485599950887, "iteration": 130 },
    { "evaluation": 93, "time": 6.293040499906056, "iteration": 131 },
    { "evaluation": 93, "time": 6.3338820999488235, "iteration": 132 },
    { "evaluation": 93, "time": 6.374536999966949, "iteration": 133 },
    { "evaluation": 93, "time": 6.41494970000349, "iteration": 134 },
    { "evaluation": 93, "time": 6.455553099978715, "iteration": 135 },
    { "evaluation": 97, "time": 6.49606869998388, "iteration": 136 },
    { "evaluation": 115, "time": 8.648353299940936, "iteration": 178 },
    { "evaluation": 115, "time": 11.115841699996963, "iteration": 220 },
    { "evaluation": 115, "time": 11.157184200012125, "iteration": 221 },
    { "evaluation": 115, "time": 11.19916399999056, "iteration": 222 },
    { "evaluation": 115, "time": 11.241163300001062, "iteration": 223 },
    { "evaluation": 115, "time": 11.28253309999127, "iteration": 224 },
    { "evaluation": 115, "time": 11.323239699937403, "iteration": 225 },
    { "evaluation": 125, "time": 11.364444599952549, "iteration": 226 },
    { "evaluation": 125, "time": 13.229596699937247, "iteration": 268 },
    { "evaluation": 125, "time": 13.27410219993908, "iteration": 269 },
    { "evaluation": 125, "time": 13.321795299998485, "iteration": 270 },
    { "evaluation": 125, "time": 13.369757700012997, "iteration": 271 },
    { "evaluation": 127, "time": 13.414355000015348, "iteration": 272 },
    { "evaluation": 127, "time": 15.239748099935241, "iteration": 314 },
    { "evaluation": 127, "time": 15.285666199983098, "iteration": 315 },
    { "evaluation": 127, "time": 15.330491699976847, "iteration": 316 },
    { "evaluation": 127, "time": 15.37495610001497, "iteration": 317 },
    { "evaluation": 127, "time": 15.42070379992947, "iteration": 318 },
    { "evaluation": 127, "time": 15.463611599989235, "iteration": 319 },
    { "evaluation": 127, "time": 15.51169299997855, "iteration": 320 },
    { "evaluation": 127, "time": 15.554639599984512, "iteration": 321 },
    { "evaluation": 127, "time": 15.596288700005971, "iteration": 322 },
    { "evaluation": 127, "time": 15.63761719991453, "iteration": 323 },
    { "evaluation": 127, "time": 15.679296199930832, "iteration": 324 },
    { "evaluation": 127, "time": 15.72078179998789, "iteration": 325 },
    { "evaluation": 127, "time": 15.762372499913909, "iteration": 326 },
    { "evaluation": 127, "time": 15.803595699951984, "iteration": 327 },
    { "evaluation": 129, "time": 15.844119799905457, "iteration": 328 },
    { "evaluation": 129, "time": 17.526642799959518, "iteration": 370 },
    { "evaluation": 129, "time": 17.567103400011547, "iteration": 371 },
    { "evaluation": 129, "time": 17.610977399977855, "iteration": 372 },
    { "evaluation": 129, "time": 17.651600299985148, "iteration": 373 },
    { "evaluation": 129, "time": 17.69174119993113, "iteration": 374 },
    { "evaluation": 129, "time": 17.7318937999662, "iteration": 375 },
    { "evaluation": 129, "time": 17.77174599992577, "iteration": 376 },
    { "evaluation": 129, "time": 17.81192879995797, "iteration": 377 },
    { "evaluation": 129, "time": 17.852242899942212, "iteration": 378 },
    { "evaluation": 129, "time": 17.893042400013655, "iteration": 379 },
    { "evaluation": 129, "time": 17.932384399930015, "iteration": 380 },
    { "evaluation": 129, "time": 17.972755299997516, "iteration": 381 },
    { "evaluation": 129, "time": 18.01318909996189, "iteration": 382 },
    { "evaluation": 129, "time": 18.053971999906935, "iteration": 383 },
    { "evaluation": 129, "time": 18.09598390001338, "iteration": 384 },
    { "evaluation": 129, "time": 18.141326099983416, "iteration": 385 },
    { "evaluation": 129, "time": 18.181883099954575, "iteration": 386 },
    { "evaluation": 129, "time": 18.221520999912173, "iteration": 387 },
    { "evaluation": 129, "time": 18.26189039996825, "iteration": 388 },
    { "evaluation": 129, "time": 18.302044000010937, "iteration": 389 },
    { "evaluation": 129, "time": 18.342187199974433, "iteration": 390 },
    { "evaluation": 129, "time": 18.382310499902815, "iteration": 391 },
    { "evaluation": 129, "time": 18.422616399941035, "iteration": 392 },
    { "evaluation": 129, "time": 18.462708599981852, "iteration": 393 },
    { "evaluation": 129, "time": 18.502778899972327, "iteration": 394 },
    { "evaluation": 129, "time": 18.54371869994793, "iteration": 395 },
    { "evaluation": 129, "time": 18.584319299901836, "iteration": 396 },
    { "evaluation": 129, "time": 18.62420849991031, "iteration": 397 },
    { "evaluation": 129, "time": 18.66798129992094, "iteration": 398 },
    { "evaluation": 129, "time": 18.70813179994002, "iteration": 399 },
    { "evaluation": 129, "time": 18.748367099906318, "iteration": 400 },
    { "evaluation": 129, "time": 18.788226599921472, "iteration": 401 },
    { "evaluation": 129, "time": 18.82807209994644, "iteration": 402 },
    { "evaluation": 129, "time": 18.868174399947748, "iteration": 403 },
    { "evaluation": 129, "time": 18.90879099990707, "iteration": 404 },
    { "evaluation": 129, "time": 18.94886449992191, "iteration": 405 },
    { "evaluation": 129, "time": 18.989466200000606, "iteration": 406 },
    { "evaluation": 129, "time": 19.031733999960124, "iteration": 407 },
    { "evaluation": 129, "time": 19.07553759997245, "iteration": 408 },
    { "evaluation": 129, "time": 19.117549399961717, "iteration": 409 },
    { "evaluation": 129, "time": 19.15956489997916, "iteration": 410 },
    { "evaluation": 129, "time": 19.206134799984284, "iteration": 411 },
    { "evaluation": 129, "time": 19.248798599932343, "iteration": 412 },
    { "evaluation": 132, "time": 19.294929199968465, "iteration": 413 },
    { "evaluation": 132, "time": 21.124420800013468, "iteration": 455 },
    { "evaluation": 132, "time": 21.166134499944746, "iteration": 456 },
    { "evaluation": 132, "time": 21.208317899960093, "iteration": 457 },
    { "evaluation": 132, "time": 21.253821899998, "iteration": 458 },
    { "evaluation": 132, "time": 21.29921729990747, "iteration": 459 },
    { "evaluation": 132, "time": 21.343425099970773, "iteration": 460 },
    { "evaluation": 132, "time": 21.386844499967992, "iteration": 461 },
    { "evaluation": 132, "time": 21.429255399969406, "iteration": 462 },
    { "evaluation": 132, "time": 21.475940999924205, "iteration": 463 },
    { "evaluation": 132, "time": 21.518764399923384, "iteration": 464 },
    { "evaluation": 132, "time": 21.561602599918842, "iteration": 465 },
    { "evaluation": 132, "time": 21.604807199910283, "iteration": 466 },
    { "evaluation": 132, "time": 21.648616999969818, "iteration": 467 },
    { "evaluation": 132, "time": 21.69623010000214, "iteration": 468 },
    { "evaluation": 132, "time": 21.74324609991163, "iteration": 469 },
    { "evaluation": 132, "time": 21.790582099929452, "iteration": 470 },
    { "evaluation": 132, "time": 21.836542399949394, "iteration": 471 },
    { "evaluation": 132, "time": 21.88226380001288, "iteration": 472 },
    { "evaluation": 132, "time": 21.92740359995514, "iteration": 473 },
    { "evaluation": 132, "time": 21.977569499984384, "iteration": 474 },
    { "evaluation": 132, "time": 22.023733499925584, "iteration": 475 },
    { "evaluation": 132, "time": 22.075726500013843, "iteration": 476 },
    { "evaluation": 132, "time": 22.121554899960756, "iteration": 477 },
    { "evaluation": 132, "time": 22.165329699986614, "iteration": 478 },
    { "evaluation": 132, "time": 22.20954559999518, "iteration": 479 },
    { "evaluation": 132, "time": 22.25254799996037, "iteration": 480 },
    { "evaluation": 132, "time": 22.295612199930474, "iteration": 481 },
    { "evaluation": 132, "time": 22.33699360000901, "iteration": 482 },
    { "evaluation": 132, "time": 22.378619999974035, "iteration": 483 },
    { "evaluation": 132, "time": 22.42010849993676, "iteration": 484 },
    { "evaluation": 132, "time": 22.461930999998003, "iteration": 485 },
    { "evaluation": 132, "time": 22.504849399905652, "iteration": 486 },
    { "evaluation": 132, "time": 22.54622409993317, "iteration": 487 },
    { "evaluation": 132, "time": 22.588489299989305, "iteration": 488 },
    { "evaluation": 132, "time": 22.63899649993982, "iteration": 489 },
    { "evaluation": 132, "time": 22.680981099954806, "iteration": 490 },
    { "evaluation": 132, "time": 22.72238389996346, "iteration": 491 },
    { "evaluation": 132, "time": 22.76430119993165, "iteration": 492 },
    { "evaluation": 132, "time": 22.805647199973464, "iteration": 493 },
    { "evaluation": 132, "time": 22.847057799925096, "iteration": 494 },
    { "evaluation": 132, "time": 22.887940099928528, "iteration": 495 },
    { "evaluation": 132, "time": 22.932080499944277, "iteration": 496 },
    { "evaluation": 132, "time": 22.976231499924324, "iteration": 497 },
    { "evaluation": 132, "time": 23.021344600012526, "iteration": 498 },
    { "evaluation": 132, "time": 23.06553519994486, "iteration": 499 },
    { "evaluation": 132, "time": 23.108567499904893, "iteration": 500 },
    { "evaluation": 132, "time": 23.15011599997524, "iteration": 501 },
    { "evaluation": 132, "time": 23.19559129991103, "iteration": 502 },
    { "evaluation": 132, "time": 23.23779869999271, "iteration": 503 },
    { "evaluation": 132, "time": 23.281598099973053, "iteration": 504 },
    { "evaluation": 132, "time": 23.32289079995826, "iteration": 505 },
    { "evaluation": 132, "time": 23.381875399965793, "iteration": 506 },
    { "evaluation": 132, "time": 23.43258889997378, "iteration": 507 },
    { "evaluation": 132, "time": 23.482008199905977, "iteration": 508 },
    { "evaluation": 132, "time": 23.530916199903004, "iteration": 509 },
    { "evaluation": 132, "time": 23.578704299987294, "iteration": 510 },
    { "evaluation": 132, "time": 23.62516559998039, "iteration": 511 },
    { "evaluation": 132, "time": 23.67310049990192, "iteration": 512 },
    { "evaluation": 132, "time": 23.716336100012995, "iteration": 513 },
    { "evaluation": 132, "time": 23.75821050000377, "iteration": 514 },
    { "evaluation": 132, "time": 23.80433399998583, "iteration": 515 },
    { "evaluation": 132, "time": 23.845741199911572, "iteration": 516 },
    { "evaluation": 132, "time": 23.886989299906418, "iteration": 517 },
    { "evaluation": 132, "time": 23.927187699940987, "iteration": 518 },
    { "evaluation": 132, "time": 23.96753139991779, "iteration": 519 },
    { "evaluation": 133, "time": 24.008323299931362, "iteration": 520 },
    { "evaluation": 133, "time": 26.01704119995702, "iteration": 562 },
    { "evaluation": 133, "time": 26.0745775999967, "iteration": 563 },
    { "evaluation": 133, "time": 26.12645579990931, "iteration": 564 },
    { "evaluation": 133, "time": 26.17683109990321, "iteration": 565 },
    { "evaluation": 133, "time": 26.224791000015102, "iteration": 566 },
    { "evaluation": 133, "time": 26.276880099903792, "iteration": 567 },
    { "evaluation": 133, "time": 26.324408199987374, "iteration": 568 },
    { "evaluation": 133, "time": 26.36989759991411, "iteration": 569 },
    { "evaluation": 133, "time": 26.414850499946624, "iteration": 570 },
    { "evaluation": 133, "time": 26.45852039998863, "iteration": 571 },
    { "evaluation": 133, "time": 26.502335499972105, "iteration": 572 },
    { "evaluation": 133, "time": 26.546074399957433, "iteration": 573 },
    { "evaluation": 133, "time": 26.58964779996313, "iteration": 574 },
    { "evaluation": 133, "time": 26.63230990001466, "iteration": 575 },
    { "evaluation": 133, "time": 26.675027199904434, "iteration": 576 },
    { "evaluation": 133, "time": 26.71686469996348, "iteration": 577 },
    { "evaluation": 133, "time": 26.759342100005597, "iteration": 578 },
    { "evaluation": 133, "time": 26.80250539991539, "iteration": 579 },
    { "evaluation": 133, "time": 26.851697299978696, "iteration": 580 },
    { "evaluation": 133, "time": 26.898497099988163, "iteration": 581 },
    { "evaluation": 133, "time": 26.942212599911727, "iteration": 582 },
    { "evaluation": 133, "time": 26.985326499911025, "iteration": 583 },
    { "evaluation": 133, "time": 27.02932879992295, "iteration": 584 },
    { "evaluation": 133, "time": 27.096527199959382, "iteration": 585 },
    { "evaluation": 133, "time": 27.145148299983703, "iteration": 586 },
    { "evaluation": 133, "time": 27.192079299944453, "iteration": 587 },
    { "evaluation": 133, "time": 27.239077399950475, "iteration": 588 },
    { "evaluation": 133, "time": 27.286430399981327, "iteration": 589 },
    { "evaluation": 133, "time": 27.331373899942264, "iteration": 590 },
    { "evaluation": 133, "time": 27.376740899984725, "iteration": 591 },
    { "evaluation": 133, "time": 27.422654900001362, "iteration": 592 },
    { "evaluation": 133, "time": 27.471692999941297, "iteration": 593 },
    { "evaluation": 133, "time": 27.51621209993027, "iteration": 594 },
    { "evaluation": 133, "time": 27.561129899928346, "iteration": 595 },
    { "evaluation": 133, "time": 27.605254799942486, "iteration": 596 },
    { "evaluation": 133, "time": 27.65001179999672, "iteration": 597 },
    { "evaluation": 133, "time": 27.69312969991006, "iteration": 598 },
    { "evaluation": 133, "time": 27.738259200006723, "iteration": 599 },
    { "evaluation": 133, "time": 27.782327799941413, "iteration": 600 },
    { "evaluation": 133, "time": 27.827544900006615, "iteration": 601 },
    { "evaluation": 133, "time": 27.873131999978796, "iteration": 602 },
    { "evaluation": 133, "time": 27.91763149993494, "iteration": 603 },
    { "evaluation": 133, "time": 27.96099839999806, "iteration": 604 },
    { "evaluation": 133, "time": 28.00467159994878, "iteration": 605 },
    { "evaluation": 133, "time": 28.057562100002542, "iteration": 606 },
    { "evaluation": 133, "time": 28.107375699910335, "iteration": 607 },
    { "evaluation": 133, "time": 28.150979699916206, "iteration": 608 },
    { "evaluation": 133, "time": 28.194948899908923, "iteration": 609 },
    { "evaluation": 133, "time": 28.23916819994338, "iteration": 610 },
    { "evaluation": 133, "time": 28.283278499962762, "iteration": 611 },
    { "evaluation": 133, "time": 28.3266354999505, "iteration": 612 },
    { "evaluation": 133, "time": 28.370161599945277, "iteration": 613 },
    { "evaluation": 133, "time": 28.41377400001511, "iteration": 614 },
    { "evaluation": 133, "time": 28.455490999971516, "iteration": 615 },
    { "evaluation": 133, "time": 28.49747009994462, "iteration": 616 },
    { "evaluation": 133, "time": 28.54047799995169, "iteration": 617 },
    { "evaluation": 133, "time": 28.583234099904075, "iteration": 618 },
    { "evaluation": 133, "time": 28.63021889992524, "iteration": 619 },
    { "evaluation": 133, "time": 28.672088899998926, "iteration": 620 },
    { "evaluation": 133, "time": 28.713876999914646, "iteration": 621 },
    { "evaluation": 133, "time": 28.75678129994776, "iteration": 622 },
    { "evaluation": 133, "time": 28.797719199908897, "iteration": 623 },
    { "evaluation": 133, "time": 28.83963209996, "iteration": 624 },
    { "evaluation": 133, "time": 28.88295899995137, "iteration": 625 },
    { "evaluation": 133, "time": 28.924596199998632, "iteration": 626 },
    { "evaluation": 133, "time": 28.966472600004636, "iteration": 627 },
    { "evaluation": 133, "time": 29.008901199907996, "iteration": 628 },
    { "evaluation": 133, "time": 29.051645800005645, "iteration": 629 },
    { "evaluation": 133, "time": 29.093961699982174, "iteration": 630 },
    { "evaluation": 133, "time": 29.13634299999103, "iteration": 631 },
    { "evaluation": 133, "time": 29.182093199924566, "iteration": 632 },
    { "evaluation": 133, "time": 29.223959199967794, "iteration": 633 },
    { "evaluation": 133, "time": 29.266040699905716, "iteration": 634 },
    { "evaluation": 133, "time": 29.308166799950413, "iteration": 635 },
    { "evaluation": 133, "time": 29.350317899952643, "iteration": 636 },
    { "evaluation": 133, "time": 29.39228439994622, "iteration": 637 },
    { "evaluation": 133, "time": 29.43429359991569, "iteration": 638 },
    { "evaluation": 133, "time": 29.47685029997956, "iteration": 639 },
    { "evaluation": 133, "time": 29.519058999954723, "iteration": 640 },
    { "evaluation": 133, "time": 29.56081950000953, "iteration": 641 },
    { "evaluation": 133, "time": 29.604394999914803, "iteration": 642 },
    { "evaluation": 141, "time": 29.652047700015828, "iteration": 643 },
    { "evaluation": 141, "time": 31.607496100012213, "iteration": 685 },
    { "evaluation": 141, "time": 31.652214900008403, "iteration": 686 },
    { "evaluation": 141, "time": 31.695043599931523, "iteration": 687 },
    { "evaluation": 141, "time": 31.743357399944216, "iteration": 688 },
    { "evaluation": 141, "time": 31.791104799951427, "iteration": 689 },
    { "evaluation": 141, "time": 31.849239700008184, "iteration": 690 },
    { "evaluation": 141, "time": 31.89763459993992, "iteration": 691 },
    { "evaluation": 141, "time": 31.94519399991259, "iteration": 692 },
    { "evaluation": 141, "time": 31.992173700011335, "iteration": 693 },
    { "evaluation": 141, "time": 32.03750749991741, "iteration": 694 },
    { "evaluation": 141, "time": 32.08151649998035, "iteration": 695 },
    { "evaluation": 141, "time": 32.12607569992542, "iteration": 696 },
    { "evaluation": 141, "time": 32.17482429998927, "iteration": 697 },
    { "evaluation": 141, "time": 32.21850009995978, "iteration": 698 },
    { "evaluation": 141, "time": 32.26229119999334, "iteration": 699 },
    { "evaluation": 141, "time": 32.30432659992948, "iteration": 700 },
    { "evaluation": 141, "time": 32.34554070001468, "iteration": 701 },
    { "evaluation": 141, "time": 32.387176399934106, "iteration": 702 },
    { "evaluation": 141, "time": 32.42935619992204, "iteration": 703 },
    { "evaluation": 141, "time": 32.471040899981745, "iteration": 704 },
    { "evaluation": 141, "time": 32.51774379995186, "iteration": 705 },
    { "evaluation": 141, "time": 32.566635399940424, "iteration": 706 },
    { "evaluation": 141, "time": 32.62013329996262, "iteration": 707 },
    { "evaluation": 141, "time": 32.69506529998034, "iteration": 708 },
    { "evaluation": 141, "time": 32.75664699997287, "iteration": 709 },
    { "evaluation": 141, "time": 32.82420859998092, "iteration": 710 },
    { "evaluation": 141, "time": 32.87940149998758, "iteration": 711 },
    { "evaluation": 141, "time": 32.93143799994141, "iteration": 712 },
    { "evaluation": 141, "time": 32.983508899924345, "iteration": 713 },
    { "evaluation": 141, "time": 33.03344949998427, "iteration": 714 },
    { "evaluation": 141, "time": 33.086017399909906, "iteration": 715 },
    { "evaluation": 141, "time": 33.141382599947974, "iteration": 716 },
    { "evaluation": 141, "time": 33.191592399962246, "iteration": 717 },
    { "evaluation": 141, "time": 33.238859699922614, "iteration": 718 },
    { "evaluation": 141, "time": 33.286316499928944, "iteration": 719 },
    { "evaluation": 141, "time": 33.333901199977845, "iteration": 720 },
    { "evaluation": 141, "time": 33.379384299973026, "iteration": 721 },
    { "evaluation": 141, "time": 33.42510899994522, "iteration": 722 },
    { "evaluation": 141, "time": 33.47387059999164, "iteration": 723 },
    { "evaluation": 141, "time": 33.530835499987006, "iteration": 724 },
    { "evaluation": 141, "time": 33.58279719995335, "iteration": 725 },
    { "evaluation": 141, "time": 33.63495300000068, "iteration": 726 },
    { "evaluation": 141, "time": 33.684696099953726, "iteration": 727 },
    { "evaluation": 141, "time": 33.733614999917336, "iteration": 728 },
    { "evaluation": 141, "time": 33.78030589991249, "iteration": 729 },
    { "evaluation": 141, "time": 33.82698779995553, "iteration": 730 },
    { "evaluation": 141, "time": 33.87161029991694, "iteration": 731 },
    { "evaluation": 141, "time": 33.91621319996193, "iteration": 732 },
    { "evaluation": 141, "time": 33.96034170000348, "iteration": 733 },
    { "evaluation": 141, "time": 34.00646029994823, "iteration": 734 },
    { "evaluation": 141, "time": 34.068833499914035, "iteration": 735 },
    { "evaluation": 141, "time": 34.11700629990082, "iteration": 736 },
    { "evaluation": 141, "time": 34.16041289991699, "iteration": 737 },
    { "evaluation": 141, "time": 34.203388599911705, "iteration": 738 },
    { "evaluation": 141, "time": 34.24589919997379, "iteration": 739 },
    { "evaluation": 141, "time": 34.290508799953386, "iteration": 740 },
    { "evaluation": 141, "time": 34.33427909994498, "iteration": 741 },
    { "evaluation": 141, "time": 34.37676739995368, "iteration": 742 },
    { "evaluation": 141, "time": 34.419158799923025, "iteration": 743 },
    { "evaluation": 141, "time": 34.46189439995214, "iteration": 744 },
    { "evaluation": 141, "time": 34.50625450001098, "iteration": 745 },
    { "evaluation": 141, "time": 34.55004050000571, "iteration": 746 },
    { "evaluation": 141, "time": 34.59451429999899, "iteration": 747 },
    { "evaluation": 141, "time": 34.63879769993946, "iteration": 748 },
    { "evaluation": 141, "time": 34.68705659999978, "iteration": 749 },
    { "evaluation": 142, "time": 34.73133609991055, "iteration": 750 },
    { "evaluation": 142, "time": 36.49488669994753, "iteration": 792 },
    { "evaluation": 142, "time": 36.5419270999264, "iteration": 793 },
    { "evaluation": 142, "time": 36.58699819992762, "iteration": 794 },
    { "evaluation": 147, "time": 36.62986969994381, "iteration": 795 },
    { "evaluation": 147, "time": 38.5015160999028, "iteration": 837 },
    { "evaluation": 147, "time": 38.543400699971244, "iteration": 838 },
    { "evaluation": 147, "time": 38.58527589996811, "iteration": 839 },
    { "evaluation": 147, "time": 38.63110839994624, "iteration": 840 },
    { "evaluation": 147, "time": 38.672291299910285, "iteration": 841 },
    { "evaluation": 147, "time": 38.713045999989845, "iteration": 842 },
    { "evaluation": 147, "time": 38.752609499963, "iteration": 843 },
    { "evaluation": 147, "time": 38.79310909996275, "iteration": 844 },
    { "evaluation": 147, "time": 38.83433779992629, "iteration": 845 },
    { "evaluation": 147, "time": 38.87505789997522, "iteration": 846 },
    { "evaluation": 147, "time": 38.91650910000317, "iteration": 847 },
    { "evaluation": 147, "time": 38.957939799991436, "iteration": 848 },
    { "evaluation": 147, "time": 38.997878299909644, "iteration": 849 },
    { "evaluation": 147, "time": 39.038878999999724, "iteration": 850 },
    { "evaluation": 147, "time": 39.08017869992182, "iteration": 851 },
    { "evaluation": 147, "time": 39.121760300011374, "iteration": 852 },
    { "evaluation": 147, "time": 39.16694229992572, "iteration": 853 },
    { "evaluation": 147, "time": 39.207065999973565, "iteration": 854 },
    { "evaluation": 147, "time": 39.24680829991121, "iteration": 855 },
    { "evaluation": 147, "time": 39.28648539993446, "iteration": 856 },
    { "evaluation": 147, "time": 39.32713369990233, "iteration": 857 },
    { "evaluation": 147, "time": 39.36674580001272, "iteration": 858 },
    { "evaluation": 147, "time": 39.40632429998368, "iteration": 859 },
    { "evaluation": 147, "time": 39.44616769999266, "iteration": 860 },
    { "evaluation": 147, "time": 39.48620039992966, "iteration": 861 },
    { "evaluation": 147, "time": 39.52661940001417, "iteration": 862 },
    { "evaluation": 147, "time": 39.56684200000018, "iteration": 863 },
    { "evaluation": 147, "time": 39.608541299938224, "iteration": 864 },
    { "evaluation": 147, "time": 39.6529012999963, "iteration": 865 },
    { "evaluation": 147, "time": 39.70192839996889, "iteration": 866 },
    { "evaluation": 147, "time": 39.74736599996686, "iteration": 867 },
    { "evaluation": 147, "time": 39.791581099969335, "iteration": 868 },
    { "evaluation": 147, "time": 39.837427499936894, "iteration": 869 },
    { "evaluation": 147, "time": 39.88813529990148, "iteration": 870 },
    { "evaluation": 147, "time": 39.93484379991423, "iteration": 871 },
    { "evaluation": 147, "time": 39.98254309990443, "iteration": 872 },
    { "evaluation": 147, "time": 40.033244899939746, "iteration": 873 },
    { "evaluation": 147, "time": 40.08377449994441, "iteration": 874 },
    { "evaluation": 147, "time": 40.13110679993406, "iteration": 875 },
    { "evaluation": 147, "time": 40.177962499903515, "iteration": 876 },
    { "evaluation": 147, "time": 40.22233049990609, "iteration": 877 },
    { "evaluation": 147, "time": 40.266669799922965, "iteration": 878 },
    { "evaluation": 147, "time": 40.314671400003135, "iteration": 879 },
    { "evaluation": 147, "time": 40.35789759992622, "iteration": 880 },
    { "evaluation": 147, "time": 40.4006050999742, "iteration": 881 },
    { "evaluation": 147, "time": 40.44193619990256, "iteration": 882 },
    { "evaluation": 147, "time": 40.483660299913026, "iteration": 883 },
    { "evaluation": 147, "time": 40.525931300013326, "iteration": 884 },
    { "evaluation": 147, "time": 40.56783349998295, "iteration": 885 },
    { "evaluation": 147, "time": 40.609287299914286, "iteration": 886 },
    { "evaluation": 147, "time": 40.652531799976714, "iteration": 887 },
    { "evaluation": 147, "time": 40.69751179998275, "iteration": 888 },
    { "evaluation": 147, "time": 40.745438599959016, "iteration": 889 },
    { "evaluation": 147, "time": 40.79708389996085, "iteration": 890 },
    { "evaluation": 147, "time": 40.845259799971245, "iteration": 891 },
    { "evaluation": 147, "time": 40.90315149992239, "iteration": 892 },
    { "evaluation": 147, "time": 40.95271679991856, "iteration": 893 },
    { "evaluation": 147, "time": 41.00752459990326, "iteration": 894 },
    { "evaluation": 147, "time": 41.06038569996599, "iteration": 895 },
    { "evaluation": 147, "time": 41.11647489992902, "iteration": 896 },
    { "evaluation": 147, "time": 41.16889400000218, "iteration": 897 },
    { "evaluation": 147, "time": 41.21880649996456, "iteration": 898 },
    { "evaluation": 147, "time": 41.26707790000364, "iteration": 899 },
    { "evaluation": 147, "time": 41.31356529996265, "iteration": 900 },
    { "evaluation": 147, "time": 41.36020529991947, "iteration": 901 },
    { "evaluation": 147, "time": 41.405800899956375, "iteration": 902 },
    { "evaluation": 147, "time": 41.44944279990159, "iteration": 903 },
    { "evaluation": 147, "time": 41.492211299948394, "iteration": 904 },
    { "evaluation": 147, "time": 41.5399242999265, "iteration": 905 },
    { "evaluation": 147, "time": 41.58289339998737, "iteration": 906 },
    { "evaluation": 147, "time": 41.626098299981095, "iteration": 907 },
    { "evaluation": 147, "time": 41.66876039991621, "iteration": 908 },
    { "evaluation": 147, "time": 41.710540500003844, "iteration": 909 },
    { "evaluation": 147, "time": 41.75219779997133, "iteration": 910 },
    { "evaluation": 147, "time": 41.79821319994517, "iteration": 911 },
    { "evaluation": 147, "time": 41.840539400000125, "iteration": 912 },
    { "evaluation": 147, "time": 41.884026899933815, "iteration": 913 },
    { "evaluation": 147, "time": 41.92789069993887, "iteration": 914 },
    { "evaluation": 147, "time": 41.97155599994585, "iteration": 915 },
    { "evaluation": 147, "time": 42.01628380001057, "iteration": 916 },
    { "evaluation": 147, "time": 42.06285879993811, "iteration": 917 },
    { "evaluation": 147, "time": 42.11368529999163, "iteration": 918 },
    { "evaluation": 147, "time": 42.159012599964626, "iteration": 919 },
    { "evaluation": 147, "time": 42.203014399972744, "iteration": 920 },
    { "evaluation": 147, "time": 42.247300799936056, "iteration": 921 },
    { "evaluation": 147, "time": 42.29084949998651, "iteration": 922 },
    { "evaluation": 147, "time": 42.33528589992784, "iteration": 923 },
    { "evaluation": 147, "time": 42.383145199972205, "iteration": 924 },
    { "evaluation": 147, "time": 42.45483870001044, "iteration": 925 },
    { "evaluation": 147, "time": 42.52265309996437, "iteration": 926 },
    { "evaluation": 147, "time": 42.57846739992965, "iteration": 927 },
    { "evaluation": 147, "time": 42.660528199980035, "iteration": 928 },
    { "evaluation": 147, "time": 42.723636299953796, "iteration": 929 },
    { "evaluation": 147, "time": 42.77883879991714, "iteration": 930 },
    { "evaluation": 147, "time": 42.83606499992311, "iteration": 931 },
    { "evaluation": 147, "time": 42.88704159995541, "iteration": 932 },
    { "evaluation": 147, "time": 42.9382551999297, "iteration": 933 },
    { "evaluation": 147, "time": 42.98819760000333, "iteration": 934 },
    { "evaluation": 147, "time": 43.040374299976975, "iteration": 935 },
    { "evaluation": 147, "time": 43.09131729998626, "iteration": 936 },
    { "evaluation": 147, "time": 43.13965169992298, "iteration": 937 },
    { "evaluation": 147, "time": 43.19017570000142, "iteration": 938 },
    { "evaluation": 147, "time": 43.23727159993723, "iteration": 939 },
    { "evaluation": 147, "time": 43.28252899996005, "iteration": 940 },
    { "evaluation": 147, "time": 43.32568209990859, "iteration": 941 },
    { "evaluation": 147, "time": 43.36902599991299, "iteration": 942 },
    { "evaluation": 147, "time": 43.411547099938616, "iteration": 943 },
    { "evaluation": 147, "time": 43.45844879990909, "iteration": 944 },
    { "evaluation": 147, "time": 43.50063499994576, "iteration": 945 },
    { "evaluation": 147, "time": 43.542290100012906, "iteration": 946 },
    { "evaluation": 147, "time": 43.583551999996416, "iteration": 947 },
    { "evaluation": 147, "time": 43.62450249993708, "iteration": 948 },
    { "evaluation": 147, "time": 43.66711719997693, "iteration": 949 },
    { "evaluation": 147, "time": 43.70860339992214, "iteration": 950 },
    { "evaluation": 147, "time": 43.75034079991747, "iteration": 951 },
    { "evaluation": 147, "time": 43.790471399901435, "iteration": 952 },
    { "evaluation": 147, "time": 43.829800299950875, "iteration": 953 },
    { "evaluation": 147, "time": 43.86977210000623, "iteration": 954 },
    { "evaluation": 147, "time": 43.90995929995552, "iteration": 955 },
    { "evaluation": 147, "time": 43.94998129992746, "iteration": 956 },
    { "evaluation": 147, "time": 43.99424639996141, "iteration": 957 },
    { "evaluation": 147, "time": 44.034668699954636, "iteration": 958 },
    { "evaluation": 147, "time": 44.075389400008135, "iteration": 959 },
    { "evaluation": 147, "time": 44.11535819992423, "iteration": 960 },
    { "evaluation": 147, "time": 44.15480049990583, "iteration": 961 },
    { "evaluation": 147, "time": 44.194691699929535, "iteration": 962 },
    { "evaluation": 147, "time": 44.23492359998636, "iteration": 963 },
    { "evaluation": 147, "time": 44.27504909993149, "iteration": 964 },
    { "evaluation": 147, "time": 44.31534989993088, "iteration": 965 },
    { "evaluation": 147, "time": 44.355368399992585, "iteration": 966 },
    { "evaluation": 147, "time": 44.395433599944226, "iteration": 967 },
    { "evaluation": 147, "time": 44.435110199963674, "iteration": 968 },
    { "evaluation": 147, "time": 44.47542229993269, "iteration": 969 },
    { "evaluation": 147, "time": 44.51895699999295, "iteration": 970 },
    { "evaluation": 147, "time": 44.55902619997505, "iteration": 971 },
    { "evaluation": 147, "time": 44.598972799954936, "iteration": 972 },
    { "evaluation": 147, "time": 44.63933019991964, "iteration": 973 },
    { "evaluation": 147, "time": 44.6799060999183, "iteration": 974 },
    { "evaluation": 147, "time": 44.719957799999975, "iteration": 975 },
    { "evaluation": 147, "time": 44.76052849995904, "iteration": 976 },
    { "evaluation": 147, "time": 44.801125500001945, "iteration": 977 },
    { "evaluation": 147, "time": 44.84105529997032, "iteration": 978 },
    { "evaluation": 147, "time": 44.88090039999224, "iteration": 979 },
    { "evaluation": 147, "time": 44.92081589996815, "iteration": 980 },
    { "evaluation": 147, "time": 44.96056789997965, "iteration": 981 },
    { "evaluation": 147, "time": 45.00107599992771, "iteration": 982 },
    { "evaluation": 147, "time": 45.04581479995977, "iteration": 983 },
    { "evaluation": 147, "time": 45.08687259990256, "iteration": 984 },
    { "evaluation": 147, "time": 45.12763659993652, "iteration": 985 },
    { "evaluation": 147, "time": 45.16756520001218, "iteration": 986 },
    { "evaluation": 147, "time": 45.20764669997152, "iteration": 987 },
    { "evaluation": 147, "time": 45.24772240000311, "iteration": 988 },
    { "evaluation": 147, "time": 45.28798109991476, "iteration": 989 },
    { "evaluation": 147, "time": 45.32766489998903, "iteration": 990 },
    { "evaluation": 147, "time": 45.36797649995424, "iteration": 991 },
    { "evaluation": 147, "time": 45.40872850001324, "iteration": 992 },
    { "evaluation": 147, "time": 45.4486678999383, "iteration": 993 },
    { "evaluation": 147, "time": 45.48899059998803, "iteration": 994 },
    { "evaluation": 147, "time": 45.52924810000695, "iteration": 995 },
    { "evaluation": 147, "time": 45.57292979990598, "iteration": 996 },
    { "evaluation": 147, "time": 45.61394559999462, "iteration": 997 },
    { "evaluation": 147, "time": 45.654280299902894, "iteration": 998 },
    { "evaluation": 147, "time": 45.69466829998419, "iteration": 999 },
    { "evaluation": 147, "time": 45.7356587999966, "iteration": 1000 },
    { "evaluation": 147, "time": 45.77699839998968, "iteration": 1001 },
    { "evaluation": 147, "time": 45.81782130000647, "iteration": 1002 },
    { "evaluation": 147, "time": 45.857406099908985, "iteration": 1003 },
    { "evaluation": 147, "time": 45.897503299987875, "iteration": 1004 },
    { "evaluation": 147, "time": 45.937981899944134, "iteration": 1005 },
    { "evaluation": 147, "time": 45.97846869996283, "iteration": 1006 },
    { "evaluation": 147, "time": 46.018323899945244, "iteration": 1007 },
    { "evaluation": 147, "time": 46.05943049991038, "iteration": 1008 },
    { "evaluation": 147, "time": 46.103504099999554, "iteration": 1009 },
    { "evaluation": 147, "time": 46.1437803999288, "iteration": 1010 },
    { "evaluation": 147, "time": 46.18336649995763, "iteration": 1011 },
    { "evaluation": 147, "time": 46.2225097999908, "iteration": 1012 },
    { "evaluation": 147, "time": 46.26176339993253, "iteration": 1013 },
    { "evaluation": 147, "time": 46.30165069992654, "iteration": 1014 },
    { "evaluation": 147, "time": 46.342791999923065, "iteration": 1015 },
    { "evaluation": 147, "time": 46.38257579994388, "iteration": 1016 },
    { "evaluation": 147, "time": 46.42269219993614, "iteration": 1017 },
    { "evaluation": 147, "time": 46.462573800003156, "iteration": 1018 },
    { "evaluation": 147, "time": 46.50323319993913, "iteration": 1019 },
    { "evaluation": 147, "time": 46.543972999905236, "iteration": 1020 },
    { "evaluation": 147, "time": 46.583837599959224, "iteration": 1021 },
    { "evaluation": 147, "time": 46.62699539994355, "iteration": 1022 },
    { "evaluation": 147, "time": 46.66742109996267, "iteration": 1023 },
    { "evaluation": 147, "time": 46.70843239990063, "iteration": 1024 },
    { "evaluation": 147, "time": 46.74952009995468, "iteration": 1025 },
    { "evaluation": 147, "time": 46.790076899924316, "iteration": 1026 },
    { "evaluation": 147, "time": 46.830596199957654, "iteration": 1027 },
    { "evaluation": 147, "time": 46.87138229992706, "iteration": 1028 },
    { "evaluation": 147, "time": 46.911537699983455, "iteration": 1029 },
    { "evaluation": 147, "time": 46.95160319993738, "iteration": 1030 },
    { "evaluation": 147, "time": 46.99162039998919, "iteration": 1031 },
    { "evaluation": 147, "time": 47.0319337999681, "iteration": 1032 },
    { "evaluation": 147, "time": 47.0737731999252, "iteration": 1033 },
    { "evaluation": 147, "time": 47.11440540000331, "iteration": 1034 },
    { "evaluation": 147, "time": 47.158046099939384, "iteration": 1035 },
    { "evaluation": 147, "time": 47.198219100013375, "iteration": 1036 },
    { "evaluation": 147, "time": 47.23856959992554, "iteration": 1037 },
    { "evaluation": 147, "time": 47.27897220000159, "iteration": 1038 },
    { "evaluation": 147, "time": 47.31936329999007, "iteration": 1039 },
    { "evaluation": 147, "time": 47.35957949992735, "iteration": 1040 },
    { "evaluation": 147, "time": 47.39954979997128, "iteration": 1041 },
    { "evaluation": 147, "time": 47.43927909992635, "iteration": 1042 },
    { "evaluation": 147, "time": 47.479362300015055, "iteration": 1043 },
    { "evaluation": 147, "time": 47.51920749992132, "iteration": 1044 },
    { "evaluation": 147, "time": 47.55968509998638, "iteration": 1045 },
    { "evaluation": 147, "time": 47.59999829996377, "iteration": 1046 },
    { "evaluation": 147, "time": 47.6400844999589, "iteration": 1047 },
    { "evaluation": 147, "time": 47.685144099988975, "iteration": 1048 },
    { "evaluation": 147, "time": 47.72719549993053, "iteration": 1049 },
    { "evaluation": 147, "time": 47.76897259999532, "iteration": 1050 },
    { "evaluation": 147, "time": 47.8103403999703, "iteration": 1051 },
    { "evaluation": 147, "time": 47.852027499931864, "iteration": 1052 },
    { "evaluation": 147, "time": 47.89262840000447, "iteration": 1053 },
    { "evaluation": 147, "time": 47.932979699922726, "iteration": 1054 },
    { "evaluation": 147, "time": 47.97385239996947, "iteration": 1055 },
    { "evaluation": 147, "time": 48.01427219994366, "iteration": 1056 },
    { "evaluation": 147, "time": 48.0547954000067, "iteration": 1057 },
    { "evaluation": 147, "time": 48.09536159993149, "iteration": 1058 },
    { "evaluation": 147, "time": 48.13565529999323, "iteration": 1059 },
    { "evaluation": 147, "time": 48.17613789997995, "iteration": 1060 },
    { "evaluation": 147, "time": 48.22020879993215, "iteration": 1061 },
    { "evaluation": 147, "time": 48.26043409993872, "iteration": 1062 },
    { "evaluation": 147, "time": 48.30078299995512, "iteration": 1063 },
    { "evaluation": 147, "time": 48.34137569996528, "iteration": 1064 },
    { "evaluation": 147, "time": 48.38273329997901, "iteration": 1065 },
    { "evaluation": 147, "time": 48.423397599952295, "iteration": 1066 },
    { "evaluation": 147, "time": 48.463513399939984, "iteration": 1067 },
    { "evaluation": 147, "time": 48.502930699964054, "iteration": 1068 },
    { "evaluation": 147, "time": 48.54329559998587, "iteration": 1069 },
    { "evaluation": 147, "time": 48.58410069998354, "iteration": 1070 },
    { "evaluation": 147, "time": 48.62506379990373, "iteration": 1071 },
    { "evaluation": 147, "time": 48.66517139994539, "iteration": 1072 },
    { "evaluation": 147, "time": 48.70481019990984, "iteration": 1073 },
    { "evaluation": 147, "time": 48.74915739998687, "iteration": 1074 },
    { "evaluation": 147, "time": 48.7888774999883, "iteration": 1075 },
    { "evaluation": 147, "time": 48.82915189990308, "iteration": 1076 },
    { "evaluation": 147, "time": 48.868971599964425, "iteration": 1077 },
    { "evaluation": 147, "time": 48.90842639992479, "iteration": 1078 },
    { "evaluation": 147, "time": 48.94840989995282, "iteration": 1079 },
    { "evaluation": 147, "time": 48.98912319994997, "iteration": 1080 },
    { "evaluation": 147, "time": 49.03028800000902, "iteration": 1081 },
    { "evaluation": 147, "time": 49.07345789996907, "iteration": 1082 },
    { "evaluation": 147, "time": 49.11473669996485, "iteration": 1083 },
    { "evaluation": 147, "time": 49.15487580001354, "iteration": 1084 },
    { "evaluation": 147, "time": 49.19446479994804, "iteration": 1085 },
    { "evaluation": 147, "time": 49.234750899951905, "iteration": 1086 },
    { "evaluation": 147, "time": 49.2787754999008, "iteration": 1087 },
    { "evaluation": 147, "time": 49.31942849990446, "iteration": 1088 },
    { "evaluation": 147, "time": 49.35939519992098, "iteration": 1089 },
    { "evaluation": 147, "time": 49.4010249999119, "iteration": 1090 },
    { "evaluation": 147, "time": 49.44207359990105, "iteration": 1091 },
    { "evaluation": 147, "time": 49.48345199995674, "iteration": 1092 },
    { "evaluation": 147, "time": 49.525476899929345, "iteration": 1093 },
    { "evaluation": 147, "time": 49.56760690000374, "iteration": 1094 },
    { "evaluation": 147, "time": 49.60922290000599, "iteration": 1095 },
    { "evaluation": 147, "time": 49.65102879994083, "iteration": 1096 },
    { "evaluation": 147, "time": 49.6925960999215, "iteration": 1097 },
    { "evaluation": 147, "time": 49.732514199917205, "iteration": 1098 },
    { "evaluation": 147, "time": 49.772294399910606, "iteration": 1099 },
    { "evaluation": 147, "time": 49.81900269992184, "iteration": 1100 },
    { "evaluation": 147, "time": 49.85963759990409, "iteration": 1101 },
    { "evaluation": 147, "time": 49.9001385999145, "iteration": 1102 },
    { "evaluation": 147, "time": 49.94284409994725, "iteration": 1103 },
    { "evaluation": 147, "time": 49.98537609993946, "iteration": 1104 },
    { "evaluation": 147, "time": 50.0260901999427, "iteration": 1105 },
    { "evaluation": 147, "time": 50.06710220000241, "iteration": 1106 },
    { "evaluation": 147, "time": 50.107291999971494, "iteration": 1107 },
    { "evaluation": 147, "time": 50.14747369999532, "iteration": 1108 },
    { "evaluation": 147, "time": 50.18776199989952, "iteration": 1109 },
    { "evaluation": 147, "time": 50.2280555999605, "iteration": 1110 },
    { "evaluation": 147, "time": 50.26819209998939, "iteration": 1111 },
    { "evaluation": 147, "time": 50.30858129996341, "iteration": 1112 },
    { "evaluation": 147, "time": 50.35248299990781, "iteration": 1113 },
    { "evaluation": 147, "time": 50.393322599935345, "iteration": 1114 },
    { "evaluation": 147, "time": 50.43576069991104, "iteration": 1115 },
    { "evaluation": 147, "time": 50.47753949998878, "iteration": 1116 },
    { "evaluation": 147, "time": 50.51913309993688, "iteration": 1117 },
    { "evaluation": 147, "time": 50.56076179991942, "iteration": 1118 },
    { "evaluation": 147, "time": 50.60110239998903, "iteration": 1119 },
    { "evaluation": 147, "time": 50.64069739996921, "iteration": 1120 },
    { "evaluation": 147, "time": 50.680320099927485, "iteration": 1121 },
    { "evaluation": 147, "time": 50.720410399953835, "iteration": 1122 },
    { "evaluation": 147, "time": 50.76068209996447, "iteration": 1123 },
    { "evaluation": 147, "time": 50.80041919997893, "iteration": 1124 },
    { "evaluation": 147, "time": 50.84108609997202, "iteration": 1125 },
    { "evaluation": 147, "time": 50.885534600005485, "iteration": 1126 },
    { "evaluation": 147, "time": 50.92581269994844, "iteration": 1127 },
    { "evaluation": 147, "time": 50.96705689991359, "iteration": 1128 },
    { "evaluation": 147, "time": 51.006753999972716, "iteration": 1129 },
    { "evaluation": 147, "time": 51.0475318999961, "iteration": 1130 },
    { "evaluation": 147, "time": 51.08806639991235, "iteration": 1131 },
    { "evaluation": 147, "time": 51.128507799934596, "iteration": 1132 },
    { "evaluation": 147, "time": 51.168406699900515, "iteration": 1133 },
    { "evaluation": 147, "time": 51.20818730001338, "iteration": 1134 },
    { "evaluation": 147, "time": 51.248175199958496, "iteration": 1135 },
    { "evaluation": 147, "time": 51.28840099996887, "iteration": 1136 },
    { "evaluation": 147, "time": 51.32844049995765, "iteration": 1137 },
    { "evaluation": 147, "time": 51.36890849994961, "iteration": 1138 },
    { "evaluation": 147, "time": 51.4136756999651, "iteration": 1139 },
    { "evaluation": 147, "time": 51.45366150001064, "iteration": 1140 },
    { "evaluation": 147, "time": 51.494252100004815, "iteration": 1141 },
    { "evaluation": 147, "time": 51.53486769995652, "iteration": 1142 },
    { "evaluation": 147, "time": 51.57575899991207, "iteration": 1143 },
    { "evaluation": 147, "time": 51.61632529995404, "iteration": 1144 },
    { "evaluation": 147, "time": 51.65676699997857, "iteration": 1145 },
    { "evaluation": 147, "time": 51.69746719999239, "iteration": 1146 },
    { "evaluation": 147, "time": 51.73825259995647, "iteration": 1147 },
    { "evaluation": 147, "time": 51.778964299941435, "iteration": 1148 },
    { "evaluation": 147, "time": 51.81905709998682, "iteration": 1149 },
    { "evaluation": 147, "time": 51.85864839993883, "iteration": 1150 },
    { "evaluation": 147, "time": 51.89966130000539, "iteration": 1151 },
    { "evaluation": 147, "time": 51.943988899933174, "iteration": 1152 },
    { "evaluation": 147, "time": 51.9851275999099, "iteration": 1153 },
    { "evaluation": 147, "time": 52.026653899927624, "iteration": 1154 },
    { "evaluation": 147, "time": 52.06871519994456, "iteration": 1155 },
    { "evaluation": 147, "time": 52.1095886999974, "iteration": 1156 },
    { "evaluation": 147, "time": 52.15017269994132, "iteration": 1157 },
    { "evaluation": 147, "time": 52.1908351999009, "iteration": 1158 },
    { "evaluation": 147, "time": 52.231264899950475, "iteration": 1159 },
    { "evaluation": 147, "time": 52.27199959999416, "iteration": 1160 },
    { "evaluation": 147, "time": 52.31214119994547, "iteration": 1161 },
    { "evaluation": 147, "time": 52.35171369998716, "iteration": 1162 },
    { "evaluation": 147, "time": 52.392667799955234, "iteration": 1163 },
    { "evaluation": 147, "time": 52.43357869994361, "iteration": 1164 },
    { "evaluation": 147, "time": 52.47904090001248, "iteration": 1165 },
    { "evaluation": 147, "time": 52.52063049993012, "iteration": 1166 },
    { "evaluation": 147, "time": 52.56172220001463, "iteration": 1167 },
    { "evaluation": 147, "time": 52.60237799992319, "iteration": 1168 },
    { "evaluation": 147, "time": 52.6431617999915, "iteration": 1169 },
    { "evaluation": 147, "time": 52.68314539990388, "iteration": 1170 },
    { "evaluation": 147, "time": 52.72330269997474, "iteration": 1171 },
    { "evaluation": 147, "time": 52.76381579996087, "iteration": 1172 },
    { "evaluation": 147, "time": 52.80429749994073, "iteration": 1173 },
    { "evaluation": 147, "time": 52.84475199994631, "iteration": 1174 },
    { "evaluation": 147, "time": 52.88547259999905, "iteration": 1175 },
    { "evaluation": 147, "time": 52.925614599953406, "iteration": 1176 },
    { "evaluation": 147, "time": 52.96585539996158, "iteration": 1177 },
    { "evaluation": 147, "time": 53.009893300011754, "iteration": 1178 },
    { "evaluation": 147, "time": 53.050314599997364, "iteration": 1179 },
    { "evaluation": 147, "time": 53.09125259995926, "iteration": 1180 },
    { "evaluation": 147, "time": 53.13197270000819, "iteration": 1181 },
    { "evaluation": 147, "time": 53.17258929996751, "iteration": 1182 },
    { "evaluation": 147, "time": 53.213189099915326, "iteration": 1183 },
    { "evaluation": 147, "time": 53.25369169993792, "iteration": 1184 },
    { "evaluation": 147, "time": 53.29407259996515, "iteration": 1185 },
    { "evaluation": 147, "time": 53.334154399926774, "iteration": 1186 },
    { "evaluation": 147, "time": 53.374233299982734, "iteration": 1187 },
    { "evaluation": 147, "time": 53.41523179993965, "iteration": 1188 },
    { "evaluation": 147, "time": 53.45599449996371, "iteration": 1189 },
    { "evaluation": 147, "time": 53.497006699908525, "iteration": 1190 },
    { "evaluation": 147, "time": 53.54169689991977, "iteration": 1191 },
    { "evaluation": 147, "time": 53.58242899994366, "iteration": 1192 },
    { "evaluation": 147, "time": 53.62271199992392, "iteration": 1193 },
    { "evaluation": 147, "time": 53.662815299932845, "iteration": 1194 },
    { "evaluation": 147, "time": 53.70357119990513, "iteration": 1195 },
    { "evaluation": 147, "time": 53.74361439992208, "iteration": 1196 },
    { "evaluation": 147, "time": 53.78333709994331, "iteration": 1197 },
    { "evaluation": 147, "time": 53.82360359991435, "iteration": 1198 },
    { "evaluation": 147, "time": 53.863853799994104, "iteration": 1199 },
    { "evaluation": 147, "time": 53.90712039999198, "iteration": 1200 },
    { "evaluation": 147, "time": 53.94738139992114, "iteration": 1201 },
    { "evaluation": 147, "time": 53.98778789991047, "iteration": 1202 },
    { "evaluation": 147, "time": 54.028355499962345, "iteration": 1203 },
    { "evaluation": 147, "time": 54.0740031999303, "iteration": 1204 },
    { "evaluation": 147, "time": 54.11451489990577, "iteration": 1205 },
    { "evaluation": 147, "time": 54.154712299932726, "iteration": 1206 },
    { "evaluation": 147, "time": 54.19533049990423, "iteration": 1207 },
    { "evaluation": 147, "time": 54.235421899938956, "iteration": 1208 },
    { "evaluation": 147, "time": 54.27536339999642, "iteration": 1209 },
    { "evaluation": 147, "time": 54.31552920001559, "iteration": 1210 },
    { "evaluation": 147, "time": 54.35584979993291, "iteration": 1211 },
    { "evaluation": 147, "time": 54.396269999910146, "iteration": 1212 },
    { "evaluation": 147, "time": 54.43573099991772, "iteration": 1213 },
    { "evaluation": 147, "time": 54.476632299949415, "iteration": 1214 },
    { "evaluation": 147, "time": 54.51652029994875, "iteration": 1215 },
    { "evaluation": 147, "time": 54.55692799994722, "iteration": 1216 },
    { "evaluation": 147, "time": 54.602668799925596, "iteration": 1217 },
    { "evaluation": 147, "time": 54.64419259992428, "iteration": 1218 },
    { "evaluation": 147, "time": 54.68635309999809, "iteration": 1219 },
    { "evaluation": 147, "time": 54.72695629997179, "iteration": 1220 },
    { "evaluation": 147, "time": 54.766995499958284, "iteration": 1221 },
    { "evaluation": 147, "time": 54.80749549996108, "iteration": 1222 },
    { "evaluation": 147, "time": 54.84735079994425, "iteration": 1223 },
    { "evaluation": 147, "time": 54.88776539999526, "iteration": 1224 },
    { "evaluation": 147, "time": 54.92864890000783, "iteration": 1225 },
    { "evaluation": 147, "time": 54.96934790001251, "iteration": 1226 },
    { "evaluation": 147, "time": 55.0108395999996, "iteration": 1227 },
    { "evaluation": 147, "time": 55.05345129990019, "iteration": 1228 },
    { "evaluation": 147, "time": 55.095375199918635, "iteration": 1229 },
    { "evaluation": 147, "time": 55.14121459994931, "iteration": 1230 },
    { "evaluation": 147, "time": 55.18262719991617, "iteration": 1231 },
    { "evaluation": 147, "time": 55.22339890000876, "iteration": 1232 },
    { "evaluation": 147, "time": 55.26418149995152, "iteration": 1233 },
    { "evaluation": 147, "time": 55.305946499924175, "iteration": 1234 },
    { "evaluation": 147, "time": 55.34791259991471, "iteration": 1235 },
    { "evaluation": 147, "time": 55.39034769998398, "iteration": 1236 },
    { "evaluation": 147, "time": 55.43354739993811, "iteration": 1237 },
    { "evaluation": 147, "time": 55.476030899910256, "iteration": 1238 },
    { "evaluation": 147, "time": 55.51920659991447, "iteration": 1239 },
    { "evaluation": 147, "time": 55.560924599994905, "iteration": 1240 },
    { "evaluation": 147, "time": 55.60242369992193, "iteration": 1241 },
    { "evaluation": 147, "time": 55.64450499997474, "iteration": 1242 },
    { "evaluation": 147, "time": 55.69121720001567, "iteration": 1243 },
    { "evaluation": 147, "time": 55.734593399916776, "iteration": 1244 },
    { "evaluation": 147, "time": 55.777584399911575, "iteration": 1245 },
    { "evaluation": 147, "time": 55.821078500011936, "iteration": 1246 },
    { "evaluation": 147, "time": 55.864126899978146, "iteration": 1247 },
    { "evaluation": 147, "time": 55.907692699925974, "iteration": 1248 },
    { "evaluation": 147, "time": 55.949500799993984, "iteration": 1249 },
    { "evaluation": 147, "time": 55.99115849996451, "iteration": 1250 },
    { "evaluation": 147, "time": 56.032420499948785, "iteration": 1251 },
    { "evaluation": 147, "time": 56.07579759997316, "iteration": 1252 },
    { "evaluation": 147, "time": 56.11771069990937, "iteration": 1253 },
    { "evaluation": 147, "time": 56.15947589999996, "iteration": 1254 },
    { "evaluation": 147, "time": 56.20221099990886, "iteration": 1255 },
    { "evaluation": 147, "time": 56.24716159992386, "iteration": 1256 },
    { "evaluation": 147, "time": 56.28886400000192, "iteration": 1257 },
    { "evaluation": 147, "time": 56.33082449994981, "iteration": 1258 },
    { "evaluation": 147, "time": 56.372249600011855, "iteration": 1259 },
    { "evaluation": 147, "time": 56.41380469989963, "iteration": 1260 },
    { "evaluation": 147, "time": 56.45545369992033, "iteration": 1261 },
    { "evaluation": 147, "time": 56.4955146999564, "iteration": 1262 },
    { "evaluation": 147, "time": 56.53564509993885, "iteration": 1263 },
    { "evaluation": 147, "time": 56.57579989999067, "iteration": 1264 },
    { "evaluation": 147, "time": 56.616221599979326, "iteration": 1265 },
    { "evaluation": 147, "time": 56.656312500010245, "iteration": 1266 },
    { "evaluation": 147, "time": 56.69913449999876, "iteration": 1267 },
    { "evaluation": 147, "time": 56.74541380000301, "iteration": 1268 },
    { "evaluation": 147, "time": 56.793298800010234, "iteration": 1269 },
    { "evaluation": 147, "time": 56.8380887999665, "iteration": 1270 },
    { "evaluation": 147, "time": 56.88230429997202, "iteration": 1271 },
    { "evaluation": 147, "time": 56.925838699913584, "iteration": 1272 },
    { "evaluation": 147, "time": 56.96919179998804, "iteration": 1273 },
    { "evaluation": 147, "time": 57.01144999999087, "iteration": 1274 },
    { "evaluation": 147, "time": 57.05414589995053, "iteration": 1275 },
    { "evaluation": 147, "time": 57.101949199917726, "iteration": 1276 },
    { "evaluation": 147, "time": 57.1474224999547, "iteration": 1277 },
    { "evaluation": 147, "time": 57.19165349996183, "iteration": 1278 },
    { "evaluation": 147, "time": 57.23467609996442, "iteration": 1279 },
    { "evaluation": 147, "time": 57.277941999956965, "iteration": 1280 },
    { "evaluation": 147, "time": 57.32087189995218, "iteration": 1281 },
    { "evaluation": 147, "time": 57.3668632999761, "iteration": 1282 },
    { "evaluation": 147, "time": 57.40827159991022, "iteration": 1283 },
    { "evaluation": 147, "time": 57.45054919994436, "iteration": 1284 },
    { "evaluation": 147, "time": 57.491972999996506, "iteration": 1285 },
    { "evaluation": 147, "time": 57.53354639990721, "iteration": 1286 },
    { "evaluation": 147, "time": 57.574966199928895, "iteration": 1287 },
    { "evaluation": 147, "time": 57.619141899980605, "iteration": 1288 },
    { "evaluation": 147, "time": 57.66166370001156, "iteration": 1289 },
    { "evaluation": 147, "time": 57.70407039998099, "iteration": 1290 },
    { "evaluation": 147, "time": 57.748297399957664, "iteration": 1291 },
    { "evaluation": 147, "time": 57.79179639997892, "iteration": 1292 },
    { "evaluation": 147, "time": 57.834685200010426, "iteration": 1293 },
    { "evaluation": 147, "time": 57.87738789990544, "iteration": 1294 },
    { "evaluation": 147, "time": 57.92569870001171, "iteration": 1295 },
    { "evaluation": 147, "time": 57.96949039993342, "iteration": 1296 },
    { "evaluation": 147, "time": 58.014816899900325, "iteration": 1297 },
    { "evaluation": 147, "time": 58.06310549995396, "iteration": 1298 },
    { "evaluation": 147, "time": 58.10818919993471, "iteration": 1299 },
    { "evaluation": 147, "time": 58.153219699976034, "iteration": 1300 },
    { "evaluation": 147, "time": 58.199499499984086, "iteration": 1301 },
    { "evaluation": 147, "time": 58.24362079997081, "iteration": 1302 },
    { "evaluation": 147, "time": 58.288264699978754, "iteration": 1303 },
    { "evaluation": 147, "time": 58.332222800003365, "iteration": 1304 },
    { "evaluation": 147, "time": 58.375522999907844, "iteration": 1305 },
    { "evaluation": 147, "time": 58.41854429990053, "iteration": 1306 },
    { "evaluation": 147, "time": 58.461339699919336, "iteration": 1307 },
    { "evaluation": 147, "time": 58.5066851999145, "iteration": 1308 },
    { "evaluation": 147, "time": 58.54801669996232, "iteration": 1309 },
    { "evaluation": 147, "time": 58.58939699991606, "iteration": 1310 },
    { "evaluation": 147, "time": 58.63457289990038, "iteration": 1311 },
    { "evaluation": 147, "time": 58.6805844999617, "iteration": 1312 },
    { "evaluation": 147, "time": 58.72352519992273, "iteration": 1313 },
    { "evaluation": 147, "time": 58.7657814999111, "iteration": 1314 },
    { "evaluation": 147, "time": 58.80769509996753, "iteration": 1315 },
    { "evaluation": 147, "time": 58.850651899934746, "iteration": 1316 },
    { "evaluation": 147, "time": 58.89395599998534, "iteration": 1317 },
    { "evaluation": 147, "time": 58.94141379999928, "iteration": 1318 },
    { "evaluation": 147, "time": 58.985569300013594, "iteration": 1319 },
    { "evaluation": 147, "time": 59.02870509994682, "iteration": 1320 },
    { "evaluation": 147, "time": 59.078621099935845, "iteration": 1321 },
    { "evaluation": 147, "time": 59.12237659993116, "iteration": 1322 },
    { "evaluation": 147, "time": 59.16818889998831, "iteration": 1323 },
    { "evaluation": 147, "time": 59.21406019991264, "iteration": 1324 },
    { "evaluation": 147, "time": 59.260841799899936, "iteration": 1325 },
    { "evaluation": 147, "time": 59.306074999971315, "iteration": 1326 },
    { "evaluation": 147, "time": 59.34931959991809, "iteration": 1327 },
    { "evaluation": 147, "time": 59.393629299942404, "iteration": 1328 },
    { "evaluation": 147, "time": 59.43714679998811, "iteration": 1329 },
    { "evaluation": 147, "time": 59.48132969997823, "iteration": 1330 },
    { "evaluation": 147, "time": 59.52480339992326, "iteration": 1331 },
    { "evaluation": 147, "time": 59.56823340000119, "iteration": 1332 },
    { "evaluation": 147, "time": 59.611822000006214, "iteration": 1333 },
    { "evaluation": 147, "time": 59.65945419995114, "iteration": 1334 },
    { "evaluation": 147, "time": 59.70341550000012, "iteration": 1335 },
    { "evaluation": 147, "time": 59.747556699905545, "iteration": 1336 },
    { "evaluation": 147, "time": 59.791244599968195, "iteration": 1337 },
    { "evaluation": 147, "time": 59.83742369990796, "iteration": 1338 },
    { "evaluation": 147, "time": 59.88154719991144, "iteration": 1339 },
    { "evaluation": 147, "time": 59.92674039991107, "iteration": 1340 },
    { "evaluation": 147, "time": 59.97057289991062, "iteration": 1341 },
    { "evaluation": 147, "time": 60.01581969996914, "iteration": 1342 },
    { "evaluation": 147, "time": 60.06751660001464, "iteration": 1343 },
    { "evaluation": 147, "time": 60.11823889997322, "iteration": 1344 },
    { "evaluation": 147, "time": 60.182254799990915, "iteration": 1345 },
    { "evaluation": 147, "time": 60.24439909995999, "iteration": 1346 },
    { "evaluation": 147, "time": 60.309610299998894, "iteration": 1347 },
    { "evaluation": 147, "time": 60.3633396999212, "iteration": 1348 },
    { "evaluation": 147, "time": 60.41543559997808, "iteration": 1349 },
    { "evaluation": 147, "time": 60.469373299973086, "iteration": 1350 },
    { "evaluation": 147, "time": 60.51822580001317, "iteration": 1351 },
    { "evaluation": 147, "time": 60.56900479993783, "iteration": 1352 },
    { "evaluation": 147, "time": 60.61983529990539, "iteration": 1353 },
    { "evaluation": 147, "time": 60.671485899947584, "iteration": 1354 },
    { "evaluation": 147, "time": 60.717860499979, "iteration": 1355 },
    { "evaluation": 147, "time": 60.766208299901336, "iteration": 1356 },
    { "evaluation": 147, "time": 60.812094099936076, "iteration": 1357 },
    { "evaluation": 147, "time": 60.85839810001198, "iteration": 1358 },
    { "evaluation": 147, "time": 60.90396939998027, "iteration": 1359 },
    { "evaluation": 147, "time": 60.954188799951226, "iteration": 1360 },
    { "evaluation": 147, "time": 61.00173489993904, "iteration": 1361 },
    { "evaluation": 147, "time": 61.0468547999626, "iteration": 1362 },
    { "evaluation": 147, "time": 61.09248959994875, "iteration": 1363 },
    { "evaluation": 147, "time": 61.14097879990004, "iteration": 1364 },
    { "evaluation": 147, "time": 61.18658959993627, "iteration": 1365 },
    { "evaluation": 147, "time": 61.233459100010805, "iteration": 1366 },
    { "evaluation": 147, "time": 61.280251599964686, "iteration": 1367 },
    { "evaluation": 147, "time": 61.324756199959666, "iteration": 1368 },
    { "evaluation": 147, "time": 61.37226149998605, "iteration": 1369 },
    { "evaluation": 147, "time": 61.41742319997866, "iteration": 1370 },
    { "evaluation": 147, "time": 61.46387049998157, "iteration": 1371 },
    { "evaluation": 147, "time": 61.5099087000126, "iteration": 1372 },
    { "evaluation": 147, "time": 61.55794889992103, "iteration": 1373 },
    { "evaluation": 147, "time": 61.60413589992095, "iteration": 1374 },
    { "evaluation": 147, "time": 61.65254069992807, "iteration": 1375 },
    { "evaluation": 147, "time": 61.69743770000059, "iteration": 1376 },
    { "evaluation": 147, "time": 61.74193459993694, "iteration": 1377 },
    { "evaluation": 147, "time": 61.785683599999174, "iteration": 1378 },
    { "evaluation": 147, "time": 61.830444299965166, "iteration": 1379 },
    { "evaluation": 147, "time": 61.879080899991095, "iteration": 1380 },
    { "evaluation": 147, "time": 61.92339789995458, "iteration": 1381 },
    { "evaluation": 147, "time": 61.967452400014736, "iteration": 1382 },
    { "evaluation": 147, "time": 62.01075369992759, "iteration": 1383 },
    { "evaluation": 147, "time": 62.05395869992208, "iteration": 1384 },
    { "evaluation": 147, "time": 62.10055949992966, "iteration": 1385 },
    { "evaluation": 147, "time": 62.15326549997553, "iteration": 1386 },
    { "evaluation": 147, "time": 62.20098349999171, "iteration": 1387 },
    { "evaluation": 147, "time": 62.2545540999854, "iteration": 1388 },
    { "evaluation": 147, "time": 62.30563259997871, "iteration": 1389 },
    { "evaluation": 147, "time": 62.3631101999199, "iteration": 1390 },
    { "evaluation": 147, "time": 62.419442099984735, "iteration": 1391 },
    { "evaluation": 147, "time": 62.477520799962804, "iteration": 1392 },
    { "evaluation": 147, "time": 62.548564499942586, "iteration": 1393 },
    { "evaluation": 147, "time": 62.60881060000975, "iteration": 1394 },
    { "evaluation": 147, "time": 62.65986709995195, "iteration": 1395 },
    { "evaluation": 147, "time": 62.710186499985866, "iteration": 1396 },
    { "evaluation": 147, "time": 62.7752089999849, "iteration": 1397 },
    { "evaluation": 147, "time": 62.83137649996206, "iteration": 1398 },
    { "evaluation": 147, "time": 62.89227439998649, "iteration": 1399 },
    { "evaluation": 147, "time": 62.94629290001467, "iteration": 1400 },
    { "evaluation": 147, "time": 63.00001919991337, "iteration": 1401 },
    { "evaluation": 147, "time": 63.067082899971865, "iteration": 1402 },
    { "evaluation": 147, "time": 63.11732969991863, "iteration": 1403 },
    { "evaluation": 147, "time": 63.16886579990387, "iteration": 1404 },
    { "evaluation": 147, "time": 63.2473187999567, "iteration": 1405 },
    { "evaluation": 147, "time": 63.3068524999544, "iteration": 1406 },
    { "evaluation": 147, "time": 63.361370499944314, "iteration": 1407 },
    { "evaluation": 147, "time": 63.414569000015035, "iteration": 1408 },
    { "evaluation": 147, "time": 63.474925499991514, "iteration": 1409 },
    { "evaluation": 147, "time": 63.532896899967454, "iteration": 1410 },
    { "evaluation": 147, "time": 63.586572199943475, "iteration": 1411 },
    { "evaluation": 147, "time": 63.643272499903105, "iteration": 1412 },
    { "evaluation": 147, "time": 63.694956699968316, "iteration": 1413 },
    { "evaluation": 147, "time": 63.74604829994496, "iteration": 1414 },
    { "evaluation": 147, "time": 63.79660150001291, "iteration": 1415 },
    { "evaluation": 147, "time": 63.84892149991356, "iteration": 1416 },
    { "evaluation": 147, "time": 63.899930399958976, "iteration": 1417 },
    { "evaluation": 147, "time": 63.95093749999069, "iteration": 1418 },
    { "evaluation": 147, "time": 64.00159899995197, "iteration": 1419 },
    { "evaluation": 147, "time": 64.05460179992951, "iteration": 1420 },
    { "evaluation": 147, "time": 64.10789929993916, "iteration": 1421 },
    { "evaluation": 147, "time": 64.15933229995426, "iteration": 1422 },
    { "evaluation": 147, "time": 64.210978899966, "iteration": 1423 },
    { "evaluation": 147, "time": 64.26288189995103, "iteration": 1424 },
    { "evaluation": 147, "time": 64.32146589993499, "iteration": 1425 },
    { "evaluation": 147, "time": 64.37447059992701, "iteration": 1426 },
    { "evaluation": 147, "time": 64.42759159998968, "iteration": 1427 },
    { "evaluation": 147, "time": 64.48304620001, "iteration": 1428 },
    { "evaluation": 147, "time": 64.53395889990497, "iteration": 1429 },
    { "evaluation": 147, "time": 64.58414880000055, "iteration": 1430 },
    { "evaluation": 147, "time": 64.63488219992723, "iteration": 1431 },
    { "evaluation": 147, "time": 64.6857108999975, "iteration": 1432 },
    { "evaluation": 147, "time": 64.73710669996217, "iteration": 1433 },
    { "evaluation": 147, "time": 64.78792929998599, "iteration": 1434 },
    { "evaluation": 147, "time": 64.83929059992079, "iteration": 1435 },
    { "evaluation": 147, "time": 64.91995219991077, "iteration": 1436 },
    { "evaluation": 147, "time": 64.97735649999231, "iteration": 1437 },
    { "evaluation": 147, "time": 65.03569089993834, "iteration": 1438 },
    { "evaluation": 147, "time": 65.09001199994236, "iteration": 1439 },
    { "evaluation": 147, "time": 65.14193719998002, "iteration": 1440 },
    { "evaluation": 147, "time": 65.19591959996615, "iteration": 1441 },
    { "evaluation": 147, "time": 65.24480869993567, "iteration": 1442 },
    { "evaluation": 147, "time": 65.2948514999589, "iteration": 1443 },
    { "evaluation": 147, "time": 65.35257629991975, "iteration": 1444 },
    { "evaluation": 147, "time": 65.42984220001381, "iteration": 1445 },
    { "evaluation": 147, "time": 65.50530149997212, "iteration": 1446 },
    { "evaluation": 147, "time": 65.59179719991516, "iteration": 1447 },
    { "evaluation": 147, "time": 65.6675477999961, "iteration": 1448 },
    { "evaluation": 147, "time": 65.73225589992944, "iteration": 1449 },
    { "evaluation": 147, "time": 65.82928389997687, "iteration": 1450 },
    { "evaluation": 147, "time": 65.91434379993007, "iteration": 1451 },
    { "evaluation": 147, "time": 65.99401259992737, "iteration": 1452 },
    { "evaluation": 147, "time": 66.05321509996429, "iteration": 1453 },
    { "evaluation": 147, "time": 66.11095469992142, "iteration": 1454 },
    { "evaluation": 147, "time": 66.16613139992114, "iteration": 1455 },
    { "evaluation": 147, "time": 66.21968769992236, "iteration": 1456 },
    { "evaluation": 147, "time": 66.27205799997319, "iteration": 1457 },
    { "evaluation": 147, "time": 66.34240179997869, "iteration": 1458 },
    { "evaluation": 147, "time": 66.39296540000942, "iteration": 1459 },
    { "evaluation": 147, "time": 66.4431391999824, "iteration": 1460 },
    { "evaluation": 147, "time": 66.49423909990583, "iteration": 1461 },
    { "evaluation": 147, "time": 66.54782440001145, "iteration": 1462 },
    { "evaluation": 147, "time": 66.59951649990398, "iteration": 1463 },
    { "evaluation": 147, "time": 66.65566789999139, "iteration": 1464 },
    { "evaluation": 147, "time": 66.70605779998004, "iteration": 1465 },
    { "evaluation": 147, "time": 66.75622919993475, "iteration": 1466 },
    { "evaluation": 147, "time": 66.80870459997095, "iteration": 1467 },
    { "evaluation": 147, "time": 66.86393599992152, "iteration": 1468 },
    { "evaluation": 147, "time": 66.92104119993746, "iteration": 1469 },
    { "evaluation": 147, "time": 66.97258389997296, "iteration": 1470 },
    { "evaluation": 147, "time": 67.02662569994573, "iteration": 1471 },
    { "evaluation": 147, "time": 67.0829535999801, "iteration": 1472 },
    { "evaluation": 147, "time": 67.13777279993519, "iteration": 1473 },
    { "evaluation": 147, "time": 67.19495329994243, "iteration": 1474 },
    { "evaluation": 147, "time": 67.24926720000803, "iteration": 1475 },
    { "evaluation": 147, "time": 67.313351699966, "iteration": 1476 },
    { "evaluation": 147, "time": 67.36999349994585, "iteration": 1477 },
    { "evaluation": 147, "time": 67.42070489993785, "iteration": 1478 },
    { "evaluation": 147, "time": 67.47025030001532, "iteration": 1479 },
    { "evaluation": 147, "time": 67.51994169992395, "iteration": 1480 },
    { "evaluation": 147, "time": 67.57201849995181, "iteration": 1481 },
    { "evaluation": 147, "time": 67.62634680001065, "iteration": 1482 },
    { "evaluation": 147, "time": 67.67683439992834, "iteration": 1483 },
    { "evaluation": 147, "time": 67.72642680001445, "iteration": 1484 },
    { "evaluation": 147, "time": 67.77952509990428, "iteration": 1485 },
    { "evaluation": 147, "time": 67.83312699990347, "iteration": 1486 },
    { "evaluation": 147, "time": 67.88588469999377, "iteration": 1487 },
    { "evaluation": 147, "time": 67.94098620000295, "iteration": 1488 },
    { "evaluation": 147, "time": 67.99281679990236, "iteration": 1489 },
    { "evaluation": 147, "time": 68.0988949999446, "iteration": 1490 },
    { "evaluation": 147, "time": 68.1549485999858, "iteration": 1491 },
    { "evaluation": 147, "time": 68.21543009998277, "iteration": 1492 },
    { "evaluation": 147, "time": 68.27316869993228, "iteration": 1493 },
    { "evaluation": 147, "time": 68.33855479990598, "iteration": 1494 },
    { "evaluation": 147, "time": 68.39016650000121, "iteration": 1495 },
    { "evaluation": 147, "time": 68.44079369993415, "iteration": 1496 },
    { "evaluation": 147, "time": 68.49243089999072, "iteration": 1497 },
    { "evaluation": 147, "time": 68.54497679998167, "iteration": 1498 },
    { "evaluation": 147, "time": 68.59579109994229, "iteration": 1499 },
    { "evaluation": 147, "time": 68.6576320999302, "iteration": 1500 },
    { "evaluation": 147, "time": 68.7160661999369, "iteration": 1501 },
    { "evaluation": 147, "time": 68.76793829991948, "iteration": 1502 },
    { "evaluation": 147, "time": 68.82483179995324, "iteration": 1503 },
    { "evaluation": 147, "time": 68.87884679995477, "iteration": 1504 },
    { "evaluation": 147, "time": 68.9341548999073, "iteration": 1505 },
    { "evaluation": 147, "time": 68.98972299997695, "iteration": 1506 },
    { "evaluation": 147, "time": 69.04576489992905, "iteration": 1507 },
    { "evaluation": 147, "time": 69.09857639996335, "iteration": 1508 },
    { "evaluation": 147, "time": 69.14983759995084, "iteration": 1509 },
    { "evaluation": 147, "time": 69.20087449997663, "iteration": 1510 },
    { "evaluation": 147, "time": 69.25032529991586, "iteration": 1511 },
    { "evaluation": 147, "time": 69.29880759993102, "iteration": 1512 },
    { "evaluation": 147, "time": 69.34705529990606, "iteration": 1513 },
    { "evaluation": 147, "time": 69.39583609998226, "iteration": 1514 },
    { "evaluation": 147, "time": 69.44436949992087, "iteration": 1515 },
    { "evaluation": 147, "time": 69.52084239991382, "iteration": 1516 },
    { "evaluation": 147, "time": 69.58039299992379, "iteration": 1517 },
    { "evaluation": 147, "time": 69.66330489993561, "iteration": 1518 },
    { "evaluation": 147, "time": 69.76696019992232, "iteration": 1519 },
    { "evaluation": 147, "time": 69.83502859994769, "iteration": 1520 },
    { "evaluation": 147, "time": 69.90015839994885, "iteration": 1521 },
    { "evaluation": 147, "time": 69.97644160001073, "iteration": 1522 },
    { "evaluation": 147, "time": 70.0660501999082, "iteration": 1523 },
    { "evaluation": 147, "time": 70.14524669991806, "iteration": 1524 },
    { "evaluation": 147, "time": 70.22271409991663, "iteration": 1525 },
    { "evaluation": 147, "time": 70.2833888999885, "iteration": 1526 },
    { "evaluation": 147, "time": 70.34221149992663, "iteration": 1527 },
    { "evaluation": 147, "time": 70.40164099994581, "iteration": 1528 },
    { "evaluation": 147, "time": 70.46420399995986, "iteration": 1529 },
    { "evaluation": 147, "time": 70.53723969997372, "iteration": 1530 },
    { "evaluation": 147, "time": 70.5937993999105, "iteration": 1531 },
    { "evaluation": 147, "time": 70.65970379998907, "iteration": 1532 },
    { "evaluation": 147, "time": 70.74161769996863, "iteration": 1533 },
    { "evaluation": 147, "time": 70.80925859999843, "iteration": 1534 },
    { "evaluation": 147, "time": 70.88364949997049, "iteration": 1535 },
    { "evaluation": 147, "time": 70.9506882999558, "iteration": 1536 },
    { "evaluation": 147, "time": 71.01532669994049, "iteration": 1537 },
    { "evaluation": 147, "time": 71.07960789999925, "iteration": 1538 },
    { "evaluation": 147, "time": 71.14799289999064, "iteration": 1539 },
    { "evaluation": 147, "time": 71.20502389990725, "iteration": 1540 },
    { "evaluation": 147, "time": 71.26065169996582, "iteration": 1541 },
    { "evaluation": 147, "time": 71.32122929999605, "iteration": 1542 },
    { "evaluation": 147, "time": 71.3797840999905, "iteration": 1543 },
    { "evaluation": 147, "time": 71.43659089994617, "iteration": 1544 },
    { "evaluation": 147, "time": 71.48907479993068, "iteration": 1545 },
    { "evaluation": 147, "time": 71.54271869990043, "iteration": 1546 },
    { "evaluation": 147, "time": 71.59456869994756, "iteration": 1547 },
    { "evaluation": 147, "time": 71.64872059994377, "iteration": 1548 },
    { "evaluation": 147, "time": 71.70324319996871, "iteration": 1549 },
    { "evaluation": 147, "time": 71.75562700000592, "iteration": 1550 },
    { "evaluation": 147, "time": 71.80651429994032, "iteration": 1551 },
    { "evaluation": 147, "time": 71.85842949990183, "iteration": 1552 },
    { "evaluation": 147, "time": 71.91987789992709, "iteration": 1553 },
    { "evaluation": 147, "time": 71.96794709993992, "iteration": 1554 },
    { "evaluation": 147, "time": 72.02057970000897, "iteration": 1555 },
    { "evaluation": 147, "time": 72.07032589998562, "iteration": 1556 },
    { "evaluation": 147, "time": 72.11904729995877, "iteration": 1557 },
    { "evaluation": 147, "time": 72.16627309995238, "iteration": 1558 },
    { "evaluation": 147, "time": 72.21420629997738, "iteration": 1559 },
    { "evaluation": 147, "time": 72.26271259994246, "iteration": 1560 },
    { "evaluation": 147, "time": 72.31099199992605, "iteration": 1561 },
    { "evaluation": 147, "time": 72.36012319999281, "iteration": 1562 },
    { "evaluation": 147, "time": 72.40604109992273, "iteration": 1563 },
    { "evaluation": 147, "time": 72.45171589998063, "iteration": 1564 },
    { "evaluation": 147, "time": 72.49729560001288, "iteration": 1565 },
    { "evaluation": 147, "time": 72.54263309994712, "iteration": 1566 },
    { "evaluation": 147, "time": 72.58834419993218, "iteration": 1567 },
    { "evaluation": 147, "time": 72.64142309990712, "iteration": 1568 },
    { "evaluation": 147, "time": 72.68892729992513, "iteration": 1569 },
    { "evaluation": 147, "time": 72.73687289992813, "iteration": 1570 },
    { "evaluation": 147, "time": 72.78599349991418, "iteration": 1571 },
    { "evaluation": 147, "time": 72.834906199947, "iteration": 1572 },
    { "evaluation": 147, "time": 72.88162839994766, "iteration": 1573 },
    { "evaluation": 147, "time": 72.92764269991312, "iteration": 1574 },
    { "evaluation": 147, "time": 72.97415479994379, "iteration": 1575 },
    { "evaluation": 147, "time": 73.02067979995627, "iteration": 1576 },
    { "evaluation": 147, "time": 73.06752899999265, "iteration": 1577 },
    { "evaluation": 147, "time": 73.11609789996874, "iteration": 1578 },
    { "evaluation": 147, "time": 73.16435679991264, "iteration": 1579 },
    { "evaluation": 147, "time": 73.21447090001311, "iteration": 1580 },
    { "evaluation": 147, "time": 73.26895199995488, "iteration": 1581 },
    { "evaluation": 147, "time": 73.3226396999089, "iteration": 1582 },
    { "evaluation": 147, "time": 73.37290859990753, "iteration": 1583 },
    { "evaluation": 147, "time": 73.42433199996594, "iteration": 1584 },
    { "evaluation": 147, "time": 73.47448410000652, "iteration": 1585 },
    { "evaluation": 147, "time": 73.52384699997492, "iteration": 1586 },
    { "evaluation": 147, "time": 73.57282999996096, "iteration": 1587 },
    { "evaluation": 147, "time": 73.62229739991017, "iteration": 1588 },
    { "evaluation": 147, "time": 73.67137449991424, "iteration": 1589 },
    { "evaluation": 147, "time": 73.72038630000316, "iteration": 1590 },
    { "evaluation": 147, "time": 73.7685534999473, "iteration": 1591 },
    { "evaluation": 147, "time": 73.81758749997243, "iteration": 1592 },
    { "evaluation": 147, "time": 73.86654279998038, "iteration": 1593 },
    { "evaluation": 147, "time": 73.91836129990406, "iteration": 1594 },
    { "evaluation": 147, "time": 73.96637199993711, "iteration": 1595 },
    { "evaluation": 147, "time": 74.01559540000744, "iteration": 1596 },
    { "evaluation": 147, "time": 74.06469909998123, "iteration": 1597 },
    { "evaluation": 147, "time": 74.11342879990116, "iteration": 1598 },
    { "evaluation": 147, "time": 74.16129319998436, "iteration": 1599 },
    { "evaluation": 147, "time": 74.20859699998982, "iteration": 1600 },
    { "evaluation": 147, "time": 74.25630249991082, "iteration": 1601 },
    { "evaluation": 147, "time": 74.3057158999145, "iteration": 1602 },
    { "evaluation": 147, "time": 74.35531369992532, "iteration": 1603 },
    { "evaluation": 147, "time": 74.40376909996849, "iteration": 1604 },
    { "evaluation": 147, "time": 74.45058649999555, "iteration": 1605 },
    { "evaluation": 147, "time": 74.4966199999908, "iteration": 1606 },
    { "evaluation": 147, "time": 74.54660379991401, "iteration": 1607 },
    { "evaluation": 147, "time": 74.59363929997198, "iteration": 1608 },
    { "evaluation": 147, "time": 74.6495507999789, "iteration": 1609 },
    { "evaluation": 147, "time": 74.71457849990111, "iteration": 1610 },
    { "evaluation": 147, "time": 74.76868219999596, "iteration": 1611 },
    { "evaluation": 147, "time": 74.82254279998597, "iteration": 1612 },
    { "evaluation": 147, "time": 74.87654859991744, "iteration": 1613 },
    { "evaluation": 147, "time": 74.930384999956, "iteration": 1614 },
    { "evaluation": 147, "time": 74.98163900000509, "iteration": 1615 },
    { "evaluation": 147, "time": 75.03161999990698, "iteration": 1616 },
    { "evaluation": 147, "time": 75.08126169990283, "iteration": 1617 },
    { "evaluation": 147, "time": 75.13090549991466, "iteration": 1618 },
    { "evaluation": 147, "time": 75.17962680000346, "iteration": 1619 },
    { "evaluation": 147, "time": 75.23619809991214, "iteration": 1620 },
    { "evaluation": 147, "time": 75.28778389992658, "iteration": 1621 },
    { "evaluation": 147, "time": 75.33782379992772, "iteration": 1622 },
    { "evaluation": 147, "time": 75.38879859994631, "iteration": 1623 },
    { "evaluation": 147, "time": 75.44088949996512, "iteration": 1624 },
    { "evaluation": 147, "time": 75.49128149996977, "iteration": 1625 },
    { "evaluation": 147, "time": 75.54225709999446, "iteration": 1626 },
    { "evaluation": 147, "time": 75.59260889992584, "iteration": 1627 },
    { "evaluation": 147, "time": 75.64272949995939, "iteration": 1628 },
    { "evaluation": 147, "time": 75.70272820000537, "iteration": 1629 },
    { "evaluation": 147, "time": 75.7505119999405, "iteration": 1630 },
    { "evaluation": 147, "time": 75.79803009994794, "iteration": 1631 },
    { "evaluation": 147, "time": 75.84624129999429, "iteration": 1632 },
    { "evaluation": 147, "time": 75.90082249999978, "iteration": 1633 },
    { "evaluation": 147, "time": 75.95107619999908, "iteration": 1634 },
    { "evaluation": 147, "time": 76.00532849994488, "iteration": 1635 },
    { "evaluation": 147, "time": 76.08918879996054, "iteration": 1636 },
    { "evaluation": 147, "time": 76.1832829999039, "iteration": 1637 },
    { "evaluation": 147, "time": 76.25734749995172, "iteration": 1638 },
    { "evaluation": 147, "time": 76.32933330000378, "iteration": 1639 },
    { "evaluation": 147, "time": 76.40790739993099, "iteration": 1640 },
    { "evaluation": 147, "time": 76.47902729990892, "iteration": 1641 },
    { "evaluation": 147, "time": 76.55350219993852, "iteration": 1642 },
    { "evaluation": 147, "time": 76.6147538999794, "iteration": 1643 },
    { "evaluation": 147, "time": 76.67123529990204, "iteration": 1644 },
    { "evaluation": 147, "time": 76.73448169999756, "iteration": 1645 },
    { "evaluation": 147, "time": 76.78997679997701, "iteration": 1646 },
    { "evaluation": 147, "time": 76.84312119998503, "iteration": 1647 },
    { "evaluation": 147, "time": 76.91410609998275, "iteration": 1648 },
    { "evaluation": 147, "time": 76.96667329990305, "iteration": 1649 },
    { "evaluation": 147, "time": 77.02141960000154, "iteration": 1650 },
    { "evaluation": 147, "time": 77.07618019997608, "iteration": 1651 },
    { "evaluation": 147, "time": 77.12924649997149, "iteration": 1652 },
    { "evaluation": 147, "time": 77.1797399999341, "iteration": 1653 },
    { "evaluation": 147, "time": 77.23499919997994, "iteration": 1654 },
    { "evaluation": 147, "time": 77.30470019998029, "iteration": 1655 },
    { "evaluation": 147, "time": 77.35606009990443, "iteration": 1656 },
    { "evaluation": 147, "time": 77.4062434999505, "iteration": 1657 },
    { "evaluation": 147, "time": 77.45704689994454, "iteration": 1658 },
    { "evaluation": 147, "time": 77.52232659992296, "iteration": 1659 },
    { "evaluation": 147, "time": 77.58680920000188, "iteration": 1660 },
    { "evaluation": 147, "time": 77.6391103999922, "iteration": 1661 },
    { "evaluation": 147, "time": 77.7030915999785, "iteration": 1662 },
    { "evaluation": 147, "time": 77.75601879996248, "iteration": 1663 },
    { "evaluation": 147, "time": 77.81069780001417, "iteration": 1664 },
    { "evaluation": 147, "time": 77.8624656999018, "iteration": 1665 },
    { "evaluation": 147, "time": 77.91524699993897, "iteration": 1666 },
    { "evaluation": 147, "time": 77.97333549999166, "iteration": 1667 },
    { "evaluation": 147, "time": 78.02767549990676, "iteration": 1668 },
    { "evaluation": 147, "time": 78.08309599990025, "iteration": 1669 },
    { "evaluation": 147, "time": 78.14009140001144, "iteration": 1670 },
    { "evaluation": 147, "time": 78.2225105999969, "iteration": 1671 },
    { "evaluation": 147, "time": 78.30165809998289, "iteration": 1672 },
    { "evaluation": 147, "time": 78.36212479998358, "iteration": 1673 },
    { "evaluation": 147, "time": 78.43321619997732, "iteration": 1674 },
    { "evaluation": 147, "time": 78.49689249997027, "iteration": 1675 },
    { "evaluation": 147, "time": 78.55236199998762, "iteration": 1676 },
    { "evaluation": 147, "time": 78.60505589994136, "iteration": 1677 },
    { "evaluation": 147, "time": 78.66178999992553, "iteration": 1678 },
    { "evaluation": 147, "time": 78.71473569993395, "iteration": 1679 },
    { "evaluation": 147, "time": 78.76812689995859, "iteration": 1680 },
    { "evaluation": 147, "time": 78.82091309991665, "iteration": 1681 },
    { "evaluation": 147, "time": 78.8903976000147, "iteration": 1682 },
    { "evaluation": 147, "time": 78.96559359994717, "iteration": 1683 },
    { "evaluation": 147, "time": 79.02522169996519, "iteration": 1684 },
    { "evaluation": 147, "time": 79.08419179997873, "iteration": 1685 },
    { "evaluation": 147, "time": 79.13781250000466, "iteration": 1686 },
    { "evaluation": 147, "time": 79.189786599949, "iteration": 1687 },
    { "evaluation": 147, "time": 79.25567159999628, "iteration": 1688 },
    { "evaluation": 147, "time": 79.30928519996814, "iteration": 1689 },
    { "evaluation": 147, "time": 79.36174229998142, "iteration": 1690 },
    { "evaluation": 147, "time": 79.41383719991427, "iteration": 1691 },
    { "evaluation": 147, "time": 79.47046849993058, "iteration": 1692 },
    { "evaluation": 147, "time": 79.5399652000051, "iteration": 1693 },
    { "evaluation": 147, "time": 79.60190959996544, "iteration": 1694 },
    { "evaluation": 147, "time": 79.65596090001054, "iteration": 1695 },
    { "evaluation": 147, "time": 79.70817719993647, "iteration": 1696 },
    { "evaluation": 147, "time": 79.76101879996713, "iteration": 1697 },
    { "evaluation": 147, "time": 79.82075149996672, "iteration": 1698 },
    { "evaluation": 147, "time": 79.87323039991315, "iteration": 1699 },
    { "evaluation": 147, "time": 79.92378959991038, "iteration": 1700 },
    { "evaluation": 147, "time": 79.97388119995594, "iteration": 1701 },
    { "evaluation": 147, "time": 80.03990139998496, "iteration": 1702 },
    { "evaluation": 147, "time": 80.09556960000191, "iteration": 1703 },
    { "evaluation": 147, "time": 80.14700609992724, "iteration": 1704 },
    { "evaluation": 147, "time": 80.20597109990194, "iteration": 1705 },
    { "evaluation": 147, "time": 80.25832929997705, "iteration": 1706 },
    { "evaluation": 147, "time": 80.31340729992371, "iteration": 1707 },
    { "evaluation": 147, "time": 80.36633959994651, "iteration": 1708 },
    { "evaluation": 147, "time": 80.42104749998543, "iteration": 1709 },
    { "evaluation": 147, "time": 80.47521279996727, "iteration": 1710 },
    { "evaluation": 147, "time": 80.54284599993844, "iteration": 1711 },
    { "evaluation": 147, "time": 80.62092489993665, "iteration": 1712 },
    { "evaluation": 147, "time": 80.68280770001002, "iteration": 1713 },
    { "evaluation": 147, "time": 80.74592299992219, "iteration": 1714 },
    { "evaluation": 147, "time": 80.8010414999444, "iteration": 1715 },
    { "evaluation": 147, "time": 80.85497240000404, "iteration": 1716 },
    { "evaluation": 147, "time": 80.90840580000076, "iteration": 1717 },
    { "evaluation": 147, "time": 80.96090569999069, "iteration": 1718 },
    { "evaluation": 147, "time": 81.01334439998027, "iteration": 1719 },
    { "evaluation": 147, "time": 81.06589949992485, "iteration": 1720 },
    { "evaluation": 147, "time": 81.11747920000926, "iteration": 1721 },
    { "evaluation": 147, "time": 81.17053879995365, "iteration": 1722 },
    { "evaluation": 147, "time": 81.22327750001568, "iteration": 1723 },
    { "evaluation": 147, "time": 81.27954249992035, "iteration": 1724 },
    { "evaluation": 147, "time": 81.3338179999264, "iteration": 1725 },
    { "evaluation": 147, "time": 81.38645310001448, "iteration": 1726 },
    { "evaluation": 147, "time": 81.44489659997635, "iteration": 1727 },
    { "evaluation": 147, "time": 81.49744309997186, "iteration": 1728 },
    { "evaluation": 147, "time": 81.55219750001561, "iteration": 1729 },
    { "evaluation": 147, "time": 81.60502949997317, "iteration": 1730 },
    { "evaluation": 147, "time": 81.6632430999307, "iteration": 1731 },
    { "evaluation": 147, "time": 81.71619579999242, "iteration": 1732 },
    { "evaluation": 147, "time": 81.76810819993261, "iteration": 1733 },
    { "evaluation": 147, "time": 81.82025109999813, "iteration": 1734 },
    { "evaluation": 147, "time": 81.87198689999059, "iteration": 1735 },
    { "evaluation": 147, "time": 81.92321559996344, "iteration": 1736 },
    { "evaluation": 147, "time": 81.97910349990707, "iteration": 1737 },
    { "evaluation": 147, "time": 82.03149119997397, "iteration": 1738 },
    { "evaluation": 147, "time": 82.08376859989949, "iteration": 1739 },
    { "evaluation": 147, "time": 82.13631739991251, "iteration": 1740 },
    { "evaluation": 147, "time": 82.1895446999697, "iteration": 1741 },
    { "evaluation": 147, "time": 82.24022869998589, "iteration": 1742 },
    { "evaluation": 147, "time": 82.28953989990987, "iteration": 1743 },
    { "evaluation": 147, "time": 82.33896570000798, "iteration": 1744 },
    { "evaluation": 147, "time": 82.39240489993244, "iteration": 1745 },
    { "evaluation": 147, "time": 82.4432639000006, "iteration": 1746 },
    { "evaluation": 147, "time": 82.49090709991287, "iteration": 1747 },
    { "evaluation": 147, "time": 82.53825829993002, "iteration": 1748 },
    { "evaluation": 147, "time": 82.59328629996162, "iteration": 1749 },
    { "evaluation": 147, "time": 82.67051969992463, "iteration": 1750 },
    { "evaluation": 147, "time": 82.73085399996489, "iteration": 1751 },
    { "evaluation": 147, "time": 82.82297199999448, "iteration": 1752 },
    { "evaluation": 147, "time": 82.90926969994325, "iteration": 1753 },
    { "evaluation": 147, "time": 82.97219839994796, "iteration": 1754 },
    { "evaluation": 147, "time": 83.0357036999194, "iteration": 1755 },
    { "evaluation": 147, "time": 83.10566489992198, "iteration": 1756 },
    { "evaluation": 147, "time": 83.18363799992949, "iteration": 1757 },
    { "evaluation": 147, "time": 83.24204349995125, "iteration": 1758 },
    { "evaluation": 147, "time": 83.29889629990794, "iteration": 1759 },
    { "evaluation": 147, "time": 83.35441379994154, "iteration": 1760 },
    { "evaluation": 147, "time": 83.40984659991227, "iteration": 1761 },
    { "evaluation": 147, "time": 83.4633324999595, "iteration": 1762 },
    { "evaluation": 147, "time": 83.52052699995693, "iteration": 1763 },
    { "evaluation": 147, "time": 83.58206829999108, "iteration": 1764 },
    { "evaluation": 147, "time": 83.65161509998143, "iteration": 1765 },
    { "evaluation": 147, "time": 83.70569420000538, "iteration": 1766 },
    { "evaluation": 147, "time": 83.75817229994573, "iteration": 1767 },
    { "evaluation": 147, "time": 83.81045320001431, "iteration": 1768 },
    { "evaluation": 147, "time": 83.861480499967, "iteration": 1769 },
    { "evaluation": 147, "time": 83.91116729995701, "iteration": 1770 },
    { "evaluation": 147, "time": 83.95968779991381, "iteration": 1771 },
    { "evaluation": 147, "time": 84.00731509993784, "iteration": 1772 },
    { "evaluation": 147, "time": 84.0575538999401, "iteration": 1773 },
    { "evaluation": 147, "time": 84.1275905999355, "iteration": 1774 },
    { "evaluation": 147, "time": 84.19137739995494, "iteration": 1775 },
    { "evaluation": 147, "time": 84.24901299993508, "iteration": 1776 },
    { "evaluation": 147, "time": 84.30023809999693, "iteration": 1777 },
    { "evaluation": 147, "time": 84.3525052999612, "iteration": 1778 },
    { "evaluation": 147, "time": 84.40619509993121, "iteration": 1779 },
    { "evaluation": 147, "time": 84.45638809993397, "iteration": 1780 },
    { "evaluation": 147, "time": 84.50618099991698, "iteration": 1781 },
    { "evaluation": 147, "time": 84.55481209990103, "iteration": 1782 },
    { "evaluation": 147, "time": 84.60388009995222, "iteration": 1783 },
    { "evaluation": 147, "time": 84.65167139994446, "iteration": 1784 },
    { "evaluation": 147, "time": 84.69944539992139, "iteration": 1785 },
    { "evaluation": 147, "time": 84.74821240000892, "iteration": 1786 },
    { "evaluation": 147, "time": 84.79595579998568, "iteration": 1787 },
    { "evaluation": 147, "time": 84.84545489994343, "iteration": 1788 },
    { "evaluation": 147, "time": 84.8980115999002, "iteration": 1789 },
    { "evaluation": 147, "time": 84.9558441999834, "iteration": 1790 },
    { "evaluation": 147, "time": 85.00716249994002, "iteration": 1791 },
    { "evaluation": 147, "time": 85.06099979998544, "iteration": 1792 },
    { "evaluation": 147, "time": 85.11269229999743, "iteration": 1793 },
    { "evaluation": 147, "time": 85.16889969992917, "iteration": 1794 },
    { "evaluation": 147, "time": 85.22788369993214, "iteration": 1795 }
  ]
}
